{
  "WorldViewTermName": {
    "WorldViewTermName_001": "[UE:Meta key=\"f4f048872eba40e6a638035d54a1a29f\" Scale=\"1\"/]cueva",
    "WorldViewTermName_002": "[UE:Meta key=\"85a1e7a201034002aab1eb57e750c8f2\" Scale=\"1\"/]zona",
    "WorldViewTermName_003": "[UE:Meta key=\"f1738f752cc045ed8e648afcec6164e3\" Scale=\"1\"/]superficie",
    "WorldViewTermName_004": "[UE:Meta key=\"a05c06b4bdf94575832806a32967f41c\" Scale=\"1\"/]subsuelo",
    "WorldViewTermName_005": "[UE:Meta key=\"5eeb3f4e5d0d487c940ba44fe3ba2742\" Scale=\"1\"/]entrada",
    "WorldViewTermName_006": "[UE:Meta key=\"ff129b418c514bd3a554a4da11451194\" Scale=\"1\"/]salida",
    "WorldViewTermName_007": "[UE:Meta key=\"e3a3e613bfe24f75a42c016f41daae68\" Scale=\"1\"/]Nivel",
    "WorldViewTermName_008": "[UE:Meta key=\"6bc6be27c3dd4a1fa7be463672879755\" Scale=\"1\"/]traje espacial",
    "WorldViewTermName_009": "[UE:Meta key=\"3712978b611c401d9defb3cd7071b1c7\" Scale=\"1\"/]silbato",
    "WorldViewTermName_010": "[UE:Meta key=\"445b1dcedb5841be8a28b9eea5a1c6fb\" Scale=\"0.9\"/]Forma de vida autóctona",
    "WorldViewTermName_011": "[UE:Meta key=\"18065f0f94684ff793e0421cb9a17908\" Scale=\"1\"/]Presa",
    "WorldViewTermName_012": "[UE:Meta key=\"ebdb55eb059048a2b7732a80b3166dee\" Scale=\"1\"/]Nutrientes",
    "WorldViewTermName_013": "[UE:Meta key=\"683326315554419bbe2d176168e8adcb\" Scale=\"1\"/]Ocaso",
    "WorldViewTermName_014": "[UE:Meta key=\"1b9b05ce04df4782a2b6e17662310764\" Scale=\"1\"/]Alba",
    "WorldViewTermName_015": "[UE:Meta key=\"e83c30cb47cb4188b3d5f701654c7edd\" Scale=\"1\"/]Área segura",
    "WorldViewTermName_016": "[UE:Meta key=\"b2398c8a6f6b4925a50011145e6c7015\" Scale=\"1\"/]Dandori",
    "WorldViewTermName_017": "[UE:Meta key=\"f91304dd0d3a4ca6bffaa24aee7ef293\" Scale=\"1\"/]Tareas",
    "WorldViewTermName_018": "[UE:Meta key=\"6e8e824b899d4b2397e06967912830e0\" Scale=\"1\"/]Grupo",
    "WorldViewTermName_020": "[UE:Meta key=\"ec57cef129ea400b8530019df87791f2\" Scale=\"0.9880239\"/]¡Se acabó el tiempo!",
    "WorldViewTermName_021": "[UE:Meta key=\"5e8bd02082374e55ae7824a956ca2825\" Scale=\"1\"/]Inconsciente",
    "WorldViewTermName_022": "[UE:Meta key=\"7fca6260e69d427cac3836dcd8f6e053\" Scale=\"1\"/]Extinción",
    "WorldViewTermName_023": "[UE:Meta key=\"e8ce79ca45e14aa0ad4692b008a93cca\" Scale=\"0.9\"/]Informe de la expedición",
    "WorldViewTermName_029": "[UE:Meta key=\"82b3d841f56e442dba0af8faa19bc090\" Scale=\"1\"/]Nuevos",
    "WorldViewTermName_024": "[UE:Meta key=\"d9b44dfe53e8426da0a22918da05d973\" Scale=\"1\"/]Perdidos",
    "WorldViewTermName_025": "[UE:Meta key=\"a01ad72fdb8e4c51988b12b87e0e4581\" Scale=\"1\"/]¡Busca!",
    "WorldViewTermName_026": "[UE:Meta key=\"2e4fefad22c343ae86817497c42d2468\" Scale=\"1\"/]Recomendados",
    "WorldViewTermName_027": "[UE:Meta key=\"d0a780a8c55644f695e2bd670eb90e43\" Scale=\"1\"/]Máximo de Pikmin",
    "WorldViewTermName_028": "[UE:Meta key=\"a16df6276d4a40d48fbf6832476ad6fa\" Scale=\"1\"/]ponzoña",
    "WorldViewTermName_030": "[UE:Meta key=\"b60b3b72f54946aa93f84a0ed05c3a88\" Scale=\"1\"/]Recompensa",
    "WorldViewTermName_031": "[UE:Meta key=\"c3a242d26d014be2ac183d5882c07ac8\" Scale=\"0.9\"/]Transportes Hocotate",
    "WorldViewTermName_032": "[UE:Meta key=\"edd1214a92b24c6d9d62251cdb60421e\" Scale=\"1\"/]componentes",
    "WorldViewTermName_033": "[UE:Meta key=\"9e7b932510674393ba23a4f4fe405447\" Scale=\"1\"/]Total"
  }
}