{
  "RescueInfo": {
    "RescueInfo_Intro_Title": "[Npc:Icon chara=\"NoSpeaker\"/][UE:Meta key=\"2fa5683422014577bae494a62babc395\" Scale=\"1\"/]Prontuario",
    "RescueInfo_Intro": "[Npc:Icon chara=\"NoSpeaker\"/][UE:Meta key=\"53a01cc591f941e09be9aef714879b25\" Scale=\"1\"/]Qui troverai dei [System:Color name=\"Emphasis\" ]consigli [System:Color name=\"Default\"]lasciati dai capitani\r\nattuali e precedenti. La loro conoscenza e\r\nsaggezza ti saranno d'aiuto.",
    "RescueInfo_Intro_Author": "[Npc:Icon chara=\"NoSpeaker\"/][UE:Meta key=\"22be117c38174bd090a4b374e4fc46f4\" Scale=\"1\"/]Capitana in carica, Erma Shepherd",
    "RescueInfo_BasicControl_Title": "[Npc:Icon chara=\"NoSpeaker\"/][UE:Meta key=\"e8c531ec85ff47b38b17caba5b8436f2\" Scale=\"1\"/]Controllare i dintorni",
    "RescueInfo_BasicControl": "[Npc:Icon chara=\"NoSpeaker\"/][UE:Meta key=\"0e7fbf9026cc49dfad8e5e4d9106fa70\" Scale=\"1\"/]Guardati intorno con [PictureFont:IconData key=\"Variable_Horizon_R_Stick\" scale=\"0.64\"/] e usa [PictureFont:IconData key=\"Vertical_R_Stick\" scale=\"0.64\"/] per cambiare\r\nl'altezza. Usa [PictureFont:IconData key=\"Variable_ZL_Button\" scale=\"0.64\"/] per girarti velocemente di fronte.\r\nRicordati di stare sempre all'erta.",
    "RescueInfo_BasicControl_Yoko": "[Npc:Icon chara=\"NoSpeaker\"/][UE:Meta key=\"cbdac3f5640b406ebf0dfdf35848c3e9\" Scale=\"1\"/]Guardati intorno tenendo premuto [PictureFont:IconData key=\"Variable_R_Stick\" scale=\"0.64\"/] mentre inclini\r\n[PictureFont:IconData key=\"Variable_L_Stick_LR\" scale=\"0.64\"/]. Premi [PictureFont:IconData key=\"Variable_R_Stick\" scale=\"0.64\"/] per guardare in avanti e controllare la\r\nsituazione. Sii sempre vigile!",
    "RescueInfo_BasicControl_Author": "[Npc:Icon chara=\"NoSpeaker\"/][UE:Meta key=\"ccfb3a4723904cf398915652534c8bb9\" Scale=\"1\"/]5º capitano, Nilman Shepherd",
    "RescueInfo_SwitchFormation_Title": "[Npc:Icon chara=\"NoSpeaker\"/][UE:Meta key=\"bc0c45d734494456961ce689eeb12eba\" Scale=\"1\"/]Divisione dei compiti",
    "RescueInfo_SwitchFormation": "[Npc:Icon chara=\"NoSpeaker\"/][UE:Meta key=\"d5e6622577174093a8b0c227bf1febbc\" Scale=\"1\"/]Premi [PictureFont:IconData key=\"L_Button\" scale=\"0.64\"/] o [PictureFont:IconData key=\"R_Button\" scale=\"0.64\"/] per selezionare chi deve eseguire\r\nil tuo [System:Color name=\"Emphasis\" ]ordine[System:Color name=\"Default\"]. Premi [PictureFont:IconData key=\"L_Button\" scale=\"0.64\"/] + [PictureFont:IconData key=\"R_Button\" scale=\"0.64\"/] per selezionare\r\nvelocemente il cane da soccorso.",
    "RescueInfo_SwitchFormation_Yoko": "[Npc:Icon chara=\"NoSpeaker\"/][UE:Meta key=\"6f6608ea3b4d4be3a4146db6cde99ea3\" Scale=\"1\"/]Premi [PictureFont:IconData key=\"Variable_Double_RescueMemo_LR\" scale=\"0.64\"/] per selezionare chi vuoi che esegua\r\ni tuoi [System:Color name=\"Emphasis\" ]ordini[System:Color name=\"Default\"].",
    "RescueInfo_SwitchFormation_Author": "[Npc:Icon chara=\"NoSpeaker\"/][UE:Meta key=\"0503d88c8a914259b759e1820f2ef554\" Scale=\"1\"/]12º capitano, Kalm Shepherd",
    "RescueInfo_Dissolution_Title": "[Npc:Icon chara=\"NoSpeaker\"/][UE:Meta key=\"c47f74748f66473bbea770f697318f38\" Scale=\"1\"/]Congeda",
    "RescueInfo_Dissolution": "[Npc:Icon chara=\"NoSpeaker\"/][UE:Meta key=\"941deba3a6a34ce5abf3978aa8da24e2\" Scale=\"1\"/]Usa [PictureFont:IconData key=\"YMenu\" scale=\"0.64\"/][PictureFont:IconData key=\"Long_Press_Button\" scale=\"0.64\"/] + [PictureFont:IconData key=\"Variable_L_Stick_Up\" scale=\"0.64\"/] per lasciare nella tua squadra solo\r\ni membri selezionati. [System:Color name=\"Emphasis\" ]Congeda[System:Color name=\"Default\"] una seconda\r\nvolta quando vuoi agire in solitario.",
    "RescueInfo_Dissolution_Author": "[Npc:Icon chara=\"NoSpeaker\"/][UE:Meta key=\"8be4d9bc7e41453096faeeac45bf9ebf\" Scale=\"1\"/]21ª capitana, Danne Shepherd",
    "RescueInfo_Lockon_Title": "[Npc:Icon chara=\"NoSpeaker\"/][UE:Meta key=\"0c6b358a20ed412bbbdada0c6213be10\" Scale=\"1\"/]Aggancio automatico",
    "RescueInfo_Lockon": "[Npc:Icon chara=\"NoSpeaker\"/][UE:Meta key=\"fe410fee78b441d1b98d9c848080a2c2\" Scale=\"1\"/]Quando il cursore dell'[Grammar:Decap/][System:Color name=\"Emphasis\" ]Aggancio automatico[System:Color name=\"Default\"] indica il tuo\r\nbersaglio, premi [PictureFont:IconData key=\"ZR_Button\" scale=\"0.64\"/] per bloccare manualmente la mira.\r\nPremi di nuovo [PictureFont:IconData key=\"ZR_Button\" scale=\"0.64\"/] per rilasciare il bersaglio o cambiarlo.",
    "RescueInfo_Lockon_Author": "[Npc:Icon chara=\"NoSpeaker\"/][UE:Meta key=\"ff9824af3c34499cbf564808c9636e12\" Scale=\"1\"/]29ª capitana, Rose Shepherd",
    "RescueInfo_HappyRush_Title": "[Npc:Icon chara=\"NoSpeaker\"/][UE:Meta key=\"adea2002f99d4055addb9d61dcadb040\" Scale=\"1\"/]Scatto",
    "RescueInfo_HappyRush": "[Npc:Icon chara=\"NoSpeaker\"/][UE:Meta key=\"f17edb686f764931899edd262f4ce540\" Scale=\"1\"/]Carica la potenza del cane da soccorso al massimo\r\ncon [PictureFont:IconData key=\"Dash\" scale=\"0.64\"/][PictureFont:IconData key=\"Long_Press_Button\" scale=\"0.64\"/] e rilascia per fare uno [Grammar:Decap/][System:Color name=\"Emphasis\" ]Scatto[System:Color name=\"Default\"]. Così potrai\r\ncorrere, rompere, scuotere e sfondare di tutto!",
    "RescueInfo_HappyRush_Author": "[Npc:Icon chara=\"NoSpeaker\"/][UE:Meta key=\"c0098474f86a4c0082285e7e300cccef\" Scale=\"1\"/]38º capitano, Morgan Shepherd",
    "RescueInfo_Onegai_Title": "[Npc:Icon chara=\"NoSpeaker\"/][UE:Meta key=\"aeec804181fe46d38f5f9344d9bb3e60\" Scale=\"1\"/]Ordini",
    "RescueInfo_Onegai": "[Npc:Icon chara=\"NoSpeaker\"/][UE:Meta key=\"8d012afd8abe4c43baaee62123e1e664\" Scale=\"1\"/]Quando hai problemi a trovare un naufrago o altre\r\ncose di cui sei in cerca, usa [PictureFont:IconData key=\"YMenu\" scale=\"0.64\"/][PictureFont:IconData key=\"Long_Press_Button\" scale=\"0.64\"/] e [PictureFont:IconData key=\"Variable_L_Stick_Left\" scale=\"0.64\"/] per dare al tuo\r\ncane da soccorso l'[Grammar:Decap/][System:Color name=\"Emphasis\" ]Ordine[System:Color name=\"Default\"] di fiutarne l'odore.",
    "RescueInfo_Onegai_Author": "[Npc:Icon chara=\"NoSpeaker\"/][UE:Meta key=\"ac9ad7dbedf74863b8904d864cc4363c\" Scale=\"1\"/]44º capitano, Dave Shepherd",
    "RescueInfo_Change_Title": "[Npc:Icon chara=\"NoSpeaker\"/][UE:Meta key=\"ade26b4e66fe40f4bc348ad30ca9c5f1\" Scale=\"1\"/]Scambio",
    "RescueInfo_Change": "[Npc:Icon chara=\"NoSpeaker\"/][UE:Meta key=\"995c5ef9e128469b856d976b27b2f5df\" Scale=\"1\"/]Quando è necessario dividersi in due squadre,\r\nfai uno [Grammar:Decap/][System:Color name=\"Emphasis\" ]Scambio [System:Color name=\"Default\"]con il tuo cane da soccorso\r\nmettendolo al comando con [PictureFont:IconData key=\"YMenu\" scale=\"0.64\"/][PictureFont:IconData key=\"Long_Press_Button\" scale=\"0.64\"/] + [PictureFont:IconData key=\"Variable_L_Stick_Down\" scale=\"0.64\"/].",
    "RescueInfo_Change_Author": "[Npc:Icon chara=\"NoSpeaker\"/][UE:Meta key=\"b1d7f9b2ff7f46f68544089d8daf984c\" Scale=\"1\"/]55º capitano, Chris Shepherd",
    "RescueInfo_BugItem_Title": "[Npc:Icon chara=\"NoSpeaker\"/][UE:Meta key=\"697f72e442b54ef38a5f74258be71901\" Scale=\"1\"/]Zaino",
    "RescueInfo_BugItem": "[Npc:Icon chara=\"NoSpeaker\"/][UE:Meta key=\"ebf345fa89fc4af7afdf631c74fe50a8\" Scale=\"1\"/]Quando devi trovare l'oggetto più adatto alla\r\nsituazione, apri lo [Grammar:Decap/][System:Color name=\"Emphasis\" ]Zaino[System:Color name=\"Default\"] con [PictureFont:IconData key=\"YMenu\" scale=\"0.64\"/][PictureFont:IconData key=\"Long_Press_Button\" scale=\"0.64\"/] + [PictureFont:IconData key=\"Variable_L_Stick_Right\" scale=\"0.64\"/] e fai la\r\ntua scelta.",
    "RescueInfo_BugItem_Author": "[Npc:Icon chara=\"NoSpeaker\"/][UE:Meta key=\"12f27e807a674037bcf5b5e978d6b9dd\" Scale=\"1\"/]61º capitano, John Shepherd",
    "RescueInfo_02_Title": "[Npc:Icon chara=\"NoSpeaker\"/][UE:Meta key=\"340ed15b408d4d6fba956bdf3453a33e\" Scale=\"1\"/]Uno spuntino al volo",
    "RescueInfo_02": "[Npc:Icon chara=\"NoSpeaker\"/][UE:Meta key=\"d5ab7d64d8a04d4a8af19267e60bf1bb\" Scale=\"1\"/]Quando vuoi ricompensare il tuo cane da soccorso,\r\nvagli vicino e tieni premuto [PictureFont:IconData key=\"Toss\" scale=\"0.64\"/][PictureFont:IconData key=\"Long_Press_Button\" scale=\"0.64\"/] per tirargli un osso.",
    "RescueInfo_02_Author": "[Npc:Icon chara=\"NoSpeaker\"/][UE:Meta key=\"e99b71b1e493415f842dbd7601c4aca2\" Scale=\"1\"/]72ª capitana, Carol Shepherd",
    "RescueInfo_01_Title": "[Npc:Icon chara=\"NoSpeaker\"/][UE:Meta key=\"34ad68d45b284fc9990dced2628c172f\" Scale=\"1\"/]Inganno",
    "RescueInfo_01": "[Npc:Icon chara=\"NoSpeaker\"/][UE:Meta key=\"a68308bcbc6e4dbb98774ee8e762baf4\" Scale=\"1\"/]Se hai una bomba in mano quando una creatura\r\ngigante sta per attaccarti, [System:Color name=\"Emphasis\" ]ingannala[System:Color name=\"Default\"] per indurla\r\na mangiare la bomba invece che te.",
    "RescueInfo_01_Author": "[Npc:Icon chara=\"NoSpeaker\"/][UE:Meta key=\"be70283362f84ae38d3da51bf706be0e\" Scale=\"1\"/]83º capitano, Maya Shepherd",
    "RescueInfo_BaseMove_Title": "[Npc:Icon chara=\"NoSpeaker\"/][UE:Meta key=\"4896666af12b45fb92df046add33153e\" Scale=\"1\"/]Sposta la base",
    "RescueInfo_BaseMove": "[Npc:Icon chara=\"NoSpeaker\"/][UE:Meta key=\"ce648832adb3443d94f3745fe5dc6d61\" Scale=\"1\"/]I soccorsi non si basano solo su ciò che sai, ma anche\r\nsull'abilità di gareggiare contro il tempo. Cambia la\r\nposizione della tua [Grammar:Decap/][System:Color name=\"Emphasis\" ]Base [System:Color name=\"Default\"]per minimizzare i trasporti.",
    "RescueInfo_BaseMove_Author": "[Npc:Icon chara=\"NoSpeaker\"/][UE:Meta key=\"8423d4b51ba04a9797fe9ae9f3ecf2d0\" Scale=\"1\"/]91º capitano, Viz Shepherd",
    "RescueInfo_17": "[Npc:Icon chara=\"NoSpeaker\"/][UE:Meta key=\"5c4a3bc75ceb458ba2edc7891f7e8648\" Scale=\"1\"/]Il precedente capitano, mio padre, era l'emblema\r\ndella generosità. Quando arrivava una chiamata\r\ndi soccorso, si precipitava a salvare chiunque\r\navesse bisogno d'aiuto. A missione conclusa, mio\r\npadre rifiutava ogni volta qualsiasi ricompensa.\r\nE così ora, grazie alla sua generosità, la squadra\r\ndi soccorso... è al verde.",
    "RescueInfo_17_Author": "[Npc:Icon chara=\"NoSpeaker\"/][UE:Meta key=\"cf0fabf40c1542adb0c6bf71414f1b62\" Scale=\"1\"/]Capitana in carica, Erma Shepherd",
    "RescueInfo_18": "[Npc:Icon chara=\"NoSpeaker\"/][UE:Meta key=\"df47b296c1334aa9ab2d54a3a06b8275\" Scale=\"1\"/]Da quando sono diventata capitana, la posizione di\r\nresponsabile dei cani da soccorso è rimasta vacante.\r\nMa io non posso abbandonarli. La mia famiglia si è\r\npresa cura di questa razza per generazioni.\r\nHo bisogno di trovare una matricola che leghi con\r\n[Npc:EmphasisStart NpcName=\"Happy\"/]Occin[Npc:EmphasisEnd/] come ho fatto io.",
    "RescueInfo_18_Author": "[Npc:Icon chara=\"NoSpeaker\"/][UE:Meta key=\"3c4be2de55f148ed96d108ead1e931ae\" Scale=\"1\"/]Capitana in carica, Erma Shepherd",
    "RescueInfo_19": "[Npc:Icon chara=\"NoSpeaker\"/][UE:Meta key=\"468d467eb4334bf7a0fed9db61616fae\" Scale=\"1\"/]I cani da soccorso apprendono le abilità giocando.\r\nMa per far sì che considerino \"gioco\" i severi\r\nallenamenti a cui sono sottoposti, bisogna tenere\r\nalta la loro motivazione. Un modo efficace per\r\nriuscirci è lodarli quando fanno bene qualcosa.",
    "RescueInfo_19_Author": "[Npc:Icon chara=\"NoSpeaker\"/][UE:Meta key=\"f0173a4d523044d49f376babe939cb7c\" Scale=\"1\"/]Capitana in carica, Erma Shepherd",
    "RescueInfo_20": "[Npc:Icon chara=\"NoSpeaker\"/][UE:Meta key=\"6bec957f1c664466b3938fac8e1f74bf\" Scale=\"1\"/]La prima volta che ho osservato il mio pianeta natale\r\ndallo spazio ho pensato: \"Le persone che ci vivono...\r\nfanno tutte parte di un unico organismo\". I conflitti\r\nesisteranno sempre. Ma mi auguro che, un giorno,\r\nciascuno di noi inizierà a guardare chi gli sta accanto\r\ncome parte di sé.",
    "RescueInfo_20_Author": "[Npc:Icon chara=\"NoSpeaker\"/][UE:Meta key=\"0ee18123691342709941021437f80540\" Scale=\"1\"/]Capitana in carica, Erma Shepherd",
    "RescueInfo_21": "[Npc:Icon chara=\"NoSpeaker\"/][UE:Meta key=\"65ae4f38d9b54165ab3458c9b97031c1\" Scale=\"1\"/]Chi non ha a cuore le persone che ha intorno o le\r\ncreature viventi in generale... non potrà mai salvare\r\nnessuno. Passiamo molto tempo insieme ai nostri\r\ncompagni. Trattarli con rispetto e premura è molto\r\nimportante.",
    "RescueInfo_21_Author": "[Npc:Icon chara=\"NoSpeaker\"/][UE:Meta key=\"30dcf398f8f14bab902a86fe4c8e0957\" Scale=\"1\"/]Capitana in carica, Erma Shepherd",
    "RescueInfo_22": "[Npc:Icon chara=\"NoSpeaker\"/][UE:Meta key=\"ee1c86f3e9e14bc1976c6681c6d69ef5\" Scale=\"1\"/]Abbiamo rilevato un S.O.S. da parte di un certo\r\n[Npc:EmphasisStart NpcName=\"Olimar\"/]Olimar[Npc:EmphasisEnd/]. Non immaginavo che esistessero pianeti\r\nancora sconosciuti. Ebbene, questa missione sarà\r\npericolosa. Lo sento. Per questo, il nuovo membro dei\r\nsoccorritori, [Replace:ReplaceName Index=\"PlayerName\"/] mi pare si chiami...\r\ndovrà attenderci al QG e non potrà unirsi a noi per\r\nla missione.",
    "RescueInfo_22_Author": "[Npc:Icon chara=\"NoSpeaker\"/][UE:Meta key=\"7f06dafa64a740c8affca759c72dbe42\" Scale=\"1\"/]Capitana in carica, Erma Shepherd",
    "RescueInfo_23": "[Npc:Icon chara=\"NoSpeaker\"/][UE:Meta key=\"cc8c6888f1e647bf899fad86808c94f9\" Scale=\"1\"/]Sono tormentata dai pensieri, ultimamente.\r\nI miei compagni hanno abbastanza responsabilità\r\ne autonomia? C'è qualcosa che dovrei fare in modo\r\ndiverso? Ci penso senza tregua. In qualità di\r\ncapitana, sto davvero facendo tutto il possibile\r\nper loro?",
    "RescueInfo_23_Author": "[Npc:Icon chara=\"NoSpeaker\"/][UE:Meta key=\"73772ac0855d47e4bb706c211b1843f3\" Scale=\"1\"/]Capitana in carica, Erma Shepherd",
    "RescueInfo_24": "[Npc:Icon chara=\"NoSpeaker\"/][UE:Meta key=\"5901d395e9cc4524ba2054b9dc533baa\" Scale=\"1\"/]Ora che abbiamo salvato e curato così tanti\r\nnaufraghi e sentito la loro gratitudine nei nostri\r\nconfronti... finalmente mi sento di essere all'altezza\r\ndi mio padre... e dei miei antenati. E per me non\r\nesiste ricompensa migliore! Sono fiera di quello che\r\nsono diventata! Ora che le preoccupazioni fanno\r\nparte del passato, mi sento molto più leggera.",
    "RescueInfo_24_Author": "[Npc:Icon chara=\"NoSpeaker\"/][UE:Meta key=\"ed200aa34d6347d2a494d288e860771a\" Scale=\"1\"/]Capitana in carica, Erma Shepherd",
    "RescueInfo_04": "[Npc:Icon chara=\"NoSpeaker\"/][UE:Meta key=\"92d4d0dcb6fb414cb396789c99b95d45\" Scale=\"1\"/]L'eroico salvataggio di tutti i naufraghi su di un\r\npianeta sconosciuto... Questa impresa verrà narrata\r\nper l'eternità! Cosa dire di più? [Replace:ReplaceName Index=\"PlayerName\"/]!\r\nE anche [Npc:EmphasisStart NpcName=\"Happy\"/]Occin[Npc:EmphasisEnd/]! Siete il nostro orgoglio! Grazie!",
    "RescueInfo_04_Author": "[Npc:Icon chara=\"NoSpeaker\"/][UE:Meta key=\"9380c0d99a2247b38f2c3903eecceae5\" Scale=\"1\"/]Capitana in carica, Erma Shepherd",
    "RescueInfo_05": "[Npc:Icon chara=\"NoSpeaker\"/][UE:Meta key=\"cf2646f6629c4c439b409d994688e08d\" Scale=\"1\"/]Grazie alla tecnologia ottenuta dall'esplorazione\r\nspaziale, la vita delle persone si è fatta più sicura\r\ne le richieste di soccorso in loco sono diminuite.\r\nMa i fenomeni migratori interplanetari continuano\r\na crescere e, con loro, anche il bisogno dei nostri\r\nservizi di salvataggio. Sono quindi felice di\r\nannunciarne l'espansione ai confini dell'universo!",
    "RescueInfo_05_Author": "[Npc:Icon chara=\"NoSpeaker\"/][UE:Meta key=\"8ad9da4e20f74a4185a7ad23e2c54892\" Scale=\"1\"/]82ª Capitana, Paniya Shepherd",
    "RescueInfo_06": "[Npc:Icon chara=\"NoSpeaker\"/][UE:Meta key=\"c751682fe60b45909926809f90342c32\" Scale=\"1\"/]Ce l'abbiamo fatta! Abbiamo raggiunto lo spazio!\r\nQui fuori, in questa immensità, non si ode alcun\r\nrumore. Eccetto il battito del mio cuore. Quello\r\nlo sento chiaramente. Lo spazio trabocca di\r\nopportunità! Non c'è dubbio, si tratta di un\r\ngigantesco balzo in avanti per la nostra specie.",
    "RescueInfo_06_Author": "[Npc:Icon chara=\"NoSpeaker\"/][UE:Meta key=\"90657aa15738435cb4eae2d2237dfdcb\" Scale=\"1\"/]65º Capitano, Ed Shepherd",
    "RescueInfo_07": "[Npc:Icon chara=\"NoSpeaker\"/][UE:Meta key=\"3bf4e6d457d54a34ac32f9638c1a1341\" Scale=\"1\"/]\"Anche nello spazio c'è chi è in attesa di essere\r\nsalvato\". Me lo disse mio padre una volta. Viaggiare\r\ntra le stelle e salvare i naufraghi era il suo sogno,\r\nche ora è diventato il mio. Purtroppo non l'ho ancora\r\nrealizzato. Mi rivolgo a voi, figli e nipoti miei: fate sì\r\nche quel sogno diventi realtà. Trascenderemo il\r\ntempo e lo spazio, statene certi.",
    "RescueInfo_07_Author": "[Npc:Icon chara=\"NoSpeaker\"/][UE:Meta key=\"075c9c65fc6342929d8de97a41b3d8c3\" Scale=\"1\"/]51º Capitano, Ponto Shepherd",
    "RescueInfo_09": "[Npc:Icon chara=\"NoSpeaker\"/][UE:Meta key=\"0e8dad68fc0f4fe2be36e1413173b809\" Scale=\"1\"/]Presto il nostro gruppo accoglierà nuovi soccorritori.\r\nAbbiamo infatti deciso ufficialmente di adottare dei\r\ncani da soccorso. I nostri amici canini non possono\r\nparlare, ma grazie all'addestramento instaureremo\r\nun duraturo legame di fiducia reciproca. Il loro fiuto\r\nrivoluzionerà il nostro modo di lavorare e verrà\r\nscritto nei libri di storia.",
    "RescueInfo_09_Author": "[Npc:Icon chara=\"NoSpeaker\"/][UE:Meta key=\"338a2bcb33db4d939af9105fcd92aa63\" Scale=\"1\"/]36º Capitano, Red Shepherd",
    "RescueInfo_10": "[Npc:Icon chara=\"NoSpeaker\"/][UE:Meta key=\"96ebeba13edb40cb88ad34fa5d6073a3\" Scale=\"1\"/]Le persone non sono brave a percepire le emozioni.\r\nAl contrario dei cani... Loro capiscono al volo cosa\r\nprovi e ti si affezionano in un baleno. Pensavo che,\r\nse i nostri cani fiutassero non solo l'odore dei\r\nnaufraghi, ma anche le loro emozioni, le nostre\r\nmissioni di salvataggio migliorerebbero\r\nenormemente.",
    "RescueInfo_10_Author": "[Npc:Icon chara=\"NoSpeaker\"/][UE:Meta key=\"f4902201c1d040dc9dd0b0dcf50555ee\" Scale=\"1\"/]29ª Capitana, Rose Shepherd",
    "RescueInfo_11": "[Npc:Icon chara=\"NoSpeaker\"/][UE:Meta key=\"a2c66eafa76946c9a301952c3fe07fc7\" Scale=\"1\"/]La famiglia Shepherd ha sempre vissuto insieme\r\nai cani. Siamo consapevoli del fatto che, amando\r\ne rispettando queste creature come se fossero\r\npersone, riusciamo a frantumare la barriera che\r\nci separa e, attraverso un'attenta osservazione del\r\nloro comportamento, possiamo giungere alla piena\r\ncomprensione reciproca.",
    "RescueInfo_11_Author": "[Npc:Icon chara=\"NoSpeaker\"/][UE:Meta key=\"2e755ef0f6f043b3ae3d066eb97addf0\" Scale=\"1\"/]16º Capitano, Kain Shepherd",
    "RescueInfo_12": "[Npc:Icon chara=\"NoSpeaker\"/][UE:Meta key=\"d878c6c4713c45d8832bbdbf6ae2411b\" Scale=\"1\"/]\"Oltre il cielo esiste uno splendido pianeta azzurro\".\r\nQueste parole vengono tramandate da capitano a\r\ncapitano. Non riesco a immaginare che posto sia\r\nquesto pianeta azzurro, ma si dice che ospiti più\r\ncani che persone, almeno in confronto alla nostra\r\npopolazione. Un giorno vorrei superare i confini\r\ndel cielo... e lanciarmi nello spazio.",
    "RescueInfo_12_Author": "[Npc:Icon chara=\"NoSpeaker\"/][UE:Meta key=\"125ecaf03081444087fd1320e64bf410\" Scale=\"1\"/]7ª Capitana, Maris Shepherd",
    "RescueInfo_14": "[Npc:Icon chara=\"NoSpeaker\"/][UE:Meta key=\"c02a699460c54d6db82b11630f4775e3\" Scale=\"1\"/]Sono passati molti anni da quando abbiamo iniziato a\r\nchiamare \"casa\" questa terra. Però ci serve ancora\r\ndel tempo per adattarci completamente al suo\r\nhabitat. Nel frattempo dobbiamo sopravvivere,\r\naffinché un giorno questa nuova storia venga\r\ntrasmessa ai nostri figli, i quali impareranno come\r\nproteggere la collettività. Un giorno vivremo in pace.",
    "RescueInfo_14_Author": "[Npc:Icon chara=\"NoSpeaker\"/][UE:Meta key=\"9cefc9a7bf114d079b99f92302a4d27d\" Scale=\"1\"/]2º Capitano, Mark Shepherd",
    "RescueInfo_16": "[Npc:Icon chara=\"NoSpeaker\"/][UE:Meta key=\"3ddb8251877a48a0829583240503a156\" Scale=\"1\"/]La superficie! Ce l'abbiamo fatta! Possiamo\r\nricominciare da zero su questo pianeta. Ovviamente\r\noccorreranno mesi, forse anni, prima di costruire qui\r\nqualcosa di paragonabile a ciò che avevamo prima.\r\nMa non siamo soli. I nostri amati cani saranno al\r\nnostro fianco in questa lunga e difficile avventura.",
    "RescueInfo_16_Author": "[Npc:Icon chara=\"NoSpeaker\"/][UE:Meta key=\"75d204025c324ade96cca7dcec765bfb\" Scale=\"1\"/]1º Capitano, Aral Shepherd"
  }
}