[
  {
    "Type": "LightMapTexture2D",
    "Name": "AOMaterialMask1_8",
    "Outer": "Area011_Objects_BuiltData",
    "Class": "UScriptClass'LightMapTexture2D'",
    "Properties": {
      "ImportedSize": {
        "X": 256,
        "Y": 128
      },
      "CompressionSettings": "TC_Alpha",
      "SRGB": false
    },
    "SizeX": 256,
    "SizeY": 128,
    "PackedData": 1,
    "PixelFormat": "PF_BC4",
    "FirstMipToSerialize": 0,
    "Mips": [
      {
        "BulkData": {
          "BulkDataFlags": "BULKDATA_PayloadAtEndOfFile | BULKDATA_PayloadInSeperateFile | BULKDATA_Force_NOT_InlinePayload | BULKDATA_NoOffsetFixUp",
          "ElementCount": 16384,
          "SizeOnDisk": 16384,
          "OffsetInFile": "0x0"
        },
        "SizeX": 256,
        "SizeY": 128,
        "SizeZ": 1
      },
      {
        "BulkData": {
          "BulkDataFlags": "BULKDATA_SingleUse | BULKDATA_ForceInlinePayload",
          "ElementCount": 4096,
          "SizeOnDisk": 4096,
          "OffsetInFile": "0xC2AF"
        },
        "SizeX": 128,
        "SizeY": 64,
        "SizeZ": 1
      },
      {
        "BulkData": {
          "BulkDataFlags": "BULKDATA_SingleUse | BULKDATA_ForceInlinePayload",
          "ElementCount": 1024,
          "SizeOnDisk": 1024,
          "OffsetInFile": "0xD2D3"
        },
        "SizeX": 64,
        "SizeY": 32,
        "SizeZ": 1
      },
      {
        "BulkData": {
          "BulkDataFlags": "BULKDATA_SingleUse | BULKDATA_ForceInlinePayload",
          "ElementCount": 256,
          "SizeOnDisk": 256,
          "OffsetInFile": "0xD6F7"
        },
        "SizeX": 32,
        "SizeY": 16,
        "SizeZ": 1
      },
      {
        "BulkData": {
          "BulkDataFlags": "BULKDATA_SingleUse | BULKDATA_ForceInlinePayload",
          "ElementCount": 64,
          "SizeOnDisk": 64,
          "OffsetInFile": "0xD81B"
        },
        "SizeX": 16,
        "SizeY": 8,
        "SizeZ": 1
      },
      {
        "BulkData": {
          "BulkDataFlags": "BULKDATA_SingleUse | BULKDATA_ForceInlinePayload",
          "ElementCount": 16,
          "SizeOnDisk": 16,
          "OffsetInFile": "0xD87F"
        },
        "SizeX": 8,
        "SizeY": 4,
        "SizeZ": 1
      },
      {
        "BulkData": {
          "BulkDataFlags": "BULKDATA_SingleUse | BULKDATA_ForceInlinePayload",
          "ElementCount": 8,
          "SizeOnDisk": 8,
          "OffsetInFile": "0xD8B3"
        },
        "SizeX": 4,
        "SizeY": 4,
        "SizeZ": 1
      },
      {
        "BulkData": {
          "BulkDataFlags": "BULKDATA_SingleUse | BULKDATA_ForceInlinePayload",
          "ElementCount": 8,
          "SizeOnDisk": 8,
          "OffsetInFile": "0xD8DF"
        },
        "SizeX": 4,
        "SizeY": 4,
        "SizeZ": 1
      },
      {
        "BulkData": {
          "BulkDataFlags": "BULKDATA_SingleUse | BULKDATA_ForceInlinePayload",
          "ElementCount": 8,
          "SizeOnDisk": 8,
          "OffsetInFile": "0xD90B"
        },
        "SizeX": 4,
        "SizeY": 4,
        "SizeZ": 1
      }
    ],
    "LightmapFlags": "LMF_Streamed"
  },
  {
    "Type": "LightMapTexture2D",
    "Name": "HQ_Lightmap1_8",
    "Outer": "Area011_Objects_BuiltData",
    "Class": "UScriptClass'LightMapTexture2D'",
    "Properties": {
      "ImportedSize": {
        "X": 256,
        "Y": 256
      },
      "SRGB": false
    },
    "SizeX": 256,
    "SizeY": 256,
    "PackedData": 1,
    "PixelFormat": "PF_DXT5",
    "FirstMipToSerialize": 0,
    "Mips": [
      {
        "BulkData": {
          "BulkDataFlags": "BULKDATA_PayloadAtEndOfFile | BULKDATA_PayloadInSeperateFile | BULKDATA_Force_NOT_InlinePayload | BULKDATA_NoOffsetFixUp",
          "ElementCount": 65536,
          "SizeOnDisk": 65536,
          "OffsetInFile": "0x4000"
        },
        "SizeX": 256,
        "SizeY": 256,
        "SizeZ": 1
      },
      {
        "BulkData": {
          "BulkDataFlags": "BULKDATA_SingleUse | BULKDATA_ForceInlinePayload",
          "ElementCount": 16384,
          "SizeOnDisk": 16384,
          "OffsetInFile": "0xDA02"
        },
        "SizeX": 128,
        "SizeY": 128,
        "SizeZ": 1
      },
      {
        "BulkData": {
          "BulkDataFlags": "BULKDATA_SingleUse | BULKDATA_ForceInlinePayload",
          "ElementCount": 4096,
          "SizeOnDisk": 4096,
          "OffsetInFile": "0x11A26"
        },
        "SizeX": 64,
        "SizeY": 64,
        "SizeZ": 1
      },
      {
        "BulkData": {
          "BulkDataFlags": "BULKDATA_SingleUse | BULKDATA_ForceInlinePayload",
          "ElementCount": 1024,
          "SizeOnDisk": 1024,
          "OffsetInFile": "0x12A4A"
        },
        "SizeX": 32,
        "SizeY": 32,
        "SizeZ": 1
      },
      {
        "BulkData": {
          "BulkDataFlags": "BULKDATA_SingleUse | BULKDATA_ForceInlinePayload",
          "ElementCount": 256,
          "SizeOnDisk": 256,
          "OffsetInFile": "0x12E6E"
        },
        "SizeX": 16,
        "SizeY": 16,
        "SizeZ": 1
      },
      {
        "BulkData": {
          "BulkDataFlags": "BULKDATA_SingleUse | BULKDATA_ForceInlinePayload",
          "ElementCount": 64,
          "SizeOnDisk": 64,
          "OffsetInFile": "0x12F92"
        },
        "SizeX": 8,
        "SizeY": 8,
        "SizeZ": 1
      },
      {
        "BulkData": {
          "BulkDataFlags": "BULKDATA_SingleUse | BULKDATA_ForceInlinePayload",
          "ElementCount": 16,
          "SizeOnDisk": 16,
          "OffsetInFile": "0x12FF6"
        },
        "SizeX": 4,
        "SizeY": 4,
        "SizeZ": 1
      },
      {
        "BulkData": {
          "BulkDataFlags": "BULKDATA_SingleUse | BULKDATA_ForceInlinePayload",
          "ElementCount": 16,
          "SizeOnDisk": 16,
          "OffsetInFile": "0x1302A"
        },
        "SizeX": 4,
        "SizeY": 4,
        "SizeZ": 1
      },
      {
        "BulkData": {
          "BulkDataFlags": "BULKDATA_SingleUse | BULKDATA_ForceInlinePayload",
          "ElementCount": 16,
          "SizeOnDisk": 16,
          "OffsetInFile": "0x1305E"
        },
        "SizeX": 4,
        "SizeY": 4,
        "SizeZ": 1
      }
    ],
    "LightmapFlags": "LMF_Streamed"
  },
  {
    "Type": "LightMapTexture2D",
    "Name": "SkyOcclusion1_8",
    "Outer": "Area011_Objects_BuiltData",
    "Class": "UScriptClass'LightMapTexture2D'",
    "Properties": {
      "ImportedSize": {
        "X": 256,
        "Y": 128
      },
      "SRGB": false
    },
    "SizeX": 256,
    "SizeY": 128,
    "PackedData": 1,
    "PixelFormat": "PF_DXT5",
    "FirstMipToSerialize": 0,
    "Mips": [
      {
        "BulkData": {
          "BulkDataFlags": "BULKDATA_PayloadAtEndOfFile | BULKDATA_PayloadInSeperateFile | BULKDATA_Force_NOT_InlinePayload | BULKDATA_NoOffsetFixUp",
          "ElementCount": 32768,
          "SizeOnDisk": 32768,
          "OffsetInFile": "0x14000"
        },
        "SizeX": 256,
        "SizeY": 128,
        "SizeZ": 1
      },
      {
        "BulkData": {
          "BulkDataFlags": "BULKDATA_SingleUse | BULKDATA_ForceInlinePayload",
          "ElementCount": 8192,
          "SizeOnDisk": 8192,
          "OffsetInFile": "0x1315D"
        },
        "SizeX": 128,
        "SizeY": 64,
        "SizeZ": 1
      },
      {
        "BulkData": {
          "BulkDataFlags": "BULKDATA_SingleUse | BULKDATA_ForceInlinePayload",
          "ElementCount": 2048,
          "SizeOnDisk": 2048,
          "OffsetInFile": "0x15181"
        },
        "SizeX": 64,
        "SizeY": 32,
        "SizeZ": 1
      },
      {
        "BulkData": {
          "BulkDataFlags": "BULKDATA_SingleUse | BULKDATA_ForceInlinePayload",
          "ElementCount": 512,
          "SizeOnDisk": 512,
          "OffsetInFile": "0x159A5"
        },
        "SizeX": 32,
        "SizeY": 16,
        "SizeZ": 1
      },
      {
        "BulkData": {
          "BulkDataFlags": "BULKDATA_SingleUse | BULKDATA_ForceInlinePayload",
          "ElementCount": 128,
          "SizeOnDisk": 128,
          "OffsetInFile": "0x15BC9"
        },
        "SizeX": 16,
        "SizeY": 8,
        "SizeZ": 1
      },
      {
        "BulkData": {
          "BulkDataFlags": "BULKDATA_SingleUse | BULKDATA_ForceInlinePayload",
          "ElementCount": 32,
          "SizeOnDisk": 32,
          "OffsetInFile": "0x15C6D"
        },
        "SizeX": 8,
        "SizeY": 4,
        "SizeZ": 1
      },
      {
        "BulkData": {
          "BulkDataFlags": "BULKDATA_SingleUse | BULKDATA_ForceInlinePayload",
          "ElementCount": 16,
          "SizeOnDisk": 16,
          "OffsetInFile": "0x15CB1"
        },
        "SizeX": 4,
        "SizeY": 4,
        "SizeZ": 1
      },
      {
        "BulkData": {
          "BulkDataFlags": "BULKDATA_SingleUse | BULKDATA_ForceInlinePayload",
          "ElementCount": 16,
          "SizeOnDisk": 16,
          "OffsetInFile": "0x15CE5"
        },
        "SizeX": 4,
        "SizeY": 4,
        "SizeZ": 1
      },
      {
        "BulkData": {
          "BulkDataFlags": "BULKDATA_SingleUse | BULKDATA_ForceInlinePayload",
          "ElementCount": 16,
          "SizeOnDisk": 16,
          "OffsetInFile": "0x15D19"
        },
        "SizeX": 4,
        "SizeY": 4,
        "SizeZ": 1
      }
    ],
    "LightmapFlags": "LMF_Streamed"
  },
  {
    "Type": "MapBuildDataRegistry",
    "Name": "Area011_Objects_BuiltData",
    "Class": "UScriptClass'MapBuildDataRegistry'",
    "Properties": {
      "LevelLightingQuality": "Quality_Production"
    },
    "MeshBuildData": {
      "BD109962445C04938989439E108D4A90": {
        "LightMap": {
          "Textures": [
            {
              "ObjectName": "LightMapTexture2D'Area011_Objects_BuiltData:HQ_Lightmap1_8'",
              "ObjectPath": "/Game/Carrot4/Maps/Main/Area/Area011/Sublevels/Area011_Objects_BuiltData.1"
            },
            null
          ],
          "SkyOcclusionTexture": {
            "ObjectName": "LightMapTexture2D'Area011_Objects_BuiltData:SkyOcclusion1_8'",
            "ObjectPath": "/Game/Carrot4/Maps/Main/Area/Area011/Sublevels/Area011_Objects_BuiltData.2"
          },
          "AOMaterialMaskTexture": {
            "ObjectName": "LightMapTexture2D'Area011_Objects_BuiltData:AOMaterialMask1_8'",
            "ObjectPath": "/Game/Carrot4/Maps/Main/Area/Area011/Sublevels/Area011_Objects_BuiltData.0"
          },
          "VirtualTextures": [
            null,
            null
          ],
          "ScaleVectors": [
            {
              "X": 0.7002934,
              "Y": 0.23244359,
              "Z": 0.6631486,
              "W": 2.2325075
            },
            {
              "X": 0.38044822,
              "Y": 0.6724565,
              "Z": 0.7025593,
              "W": 0.0
            },
            {
              "X": 0.0,
              "Y": 0.0,
              "Z": 0.0,
              "W": 1.0
            },
            {
              "X": 0.0,
              "Y": 0.0,
              "Z": 0.0,
              "W": 1.0
            }
          ],
          "AddVectors": [
            {
              "X": 1.0439509,
              "Y": 0.7541331,
              "Z": 0.28898358,
              "W": -1.1227636
            },
            {
              "X": -0.15288225,
              "Y": -0.32265824,
              "Z": -0.37017384,
              "W": 0.282095
            },
            {
              "X": 0.01,
              "Y": 0.01,
              "Z": 0.01,
              "W": 1.0
            },
            {
              "X": 0.0,
              "Y": 0.0,
              "Z": 0.0,
              "W": 1.0
            }
          ],
          "CoordinateScale": {
            "X": 0.2421875,
            "Y": 0.484375
          },
          "CoordinateBias": {
            "X": 0.25390625,
            "Y": 0.5078125
          },
          "InvUniformPenumbraSize": {
            "X": 0.0,
            "Y": 0.0,
            "Z": 0.0,
            "W": 1.0
          },
          "bShadowChannelValid": [
            false,
            false,
            false,
            false
          ],
          "LightGuids": [
            "89698FFA-4F93B075-6DABA59B-0257D39B",
            "6938A531-4666229B-D438FCBA-C2C81595",
            "F5B5499D-4E86C315-53D0B498-7F159297",
            "6DC4FE64-4447B9A5-6C09CA84-7E96F320",
            "EE3601BF-4741A7BF-26E791B5-0F09B138",
            "51BD0747-40B8D23F-C9297784-B3E754F1",
            "EC9B1A16-406D20A1-AEA42BB9-A83F1F41",
            "146AF705-4C8A9F5B-4E760986-62927C9C",
            "6EECFC35-4840F2B5-5DB141AD-798E4273",
            "A27D322D-49EA9F15-B2C2EBBF-566CF1C6",
            "D9E4D333-48792B87-8DC2D689-6030B0D6"
          ]
        },
        "ShadowMap": {
          "Texture": {
            "ObjectName": "ShadowMapTexture2D'Area011_Objects_BuiltData:ShadowMapTexture2D_1'",
            "ObjectPath": "/Game/Carrot4/Maps/Main/Area/Area011/Sublevels/Area011_Objects_BuiltData.4"
          },
          "CoordinateScale": {
            "X": 0.484375,
            "Y": 0.96875
          },
          "CoordinateBias": {
            "X": 0.5078125,
            "Y": 0.015625
          },
          "bChannelValid": [
            true,
            false,
            false,
            false
          ],
          "InvUniformPenumbraSize": {
            "X": 1.0,
            "Y": 0.0,
            "Z": 0.0,
            "W": 0.0
          },
          "LightGuids": [
            "ACE03AAE-426E1985-A4708681-FFC40418"
          ]
        },
        "IrrelevantLights": [
          "1DB94F57-4012680D-67735494-8853B8C1"
        ],
        "PerInstanceLightmapData": []
      },
      "458296C44C0BF4329B3713BFC21D7D40": {
        "LightMap": {
          "Textures": [
            {
              "ObjectName": "LightMapTexture2D'Area011_Objects_BuiltData:HQ_Lightmap1_8'",
              "ObjectPath": "/Game/Carrot4/Maps/Main/Area/Area011/Sublevels/Area011_Objects_BuiltData.1"
            },
            null
          ],
          "SkyOcclusionTexture": {
            "ObjectName": "LightMapTexture2D'Area011_Objects_BuiltData:SkyOcclusion1_8'",
            "ObjectPath": "/Game/Carrot4/Maps/Main/Area/Area011/Sublevels/Area011_Objects_BuiltData.2"
          },
          "AOMaterialMaskTexture": {
            "ObjectName": "LightMapTexture2D'Area011_Objects_BuiltData:AOMaterialMask1_8'",
            "ObjectPath": "/Game/Carrot4/Maps/Main/Area/Area011/Sublevels/Area011_Objects_BuiltData.0"
          },
          "VirtualTextures": [
            null,
            null
          ],
          "ScaleVectors": [
            {
              "X": 0.813516,
              "Y": 0.30330998,
              "Z": 0.6832818,
              "W": 5.193824
            },
            {
              "X": 0.54739887,
              "Y": 0.61200476,
              "Z": 0.8556617,
              "W": 0.0
            },
            {
              "X": 0.0,
              "Y": 0.0,
              "Z": 0.0,
              "W": 1.0
            },
            {
              "X": 0.0,
              "Y": 0.0,
              "Z": 0.0,
              "W": 1.0
            }
          ],
          "AddVectors": [
            {
              "X": 1.0060103,
              "Y": 0.6923184,
              "Z": 0.32377532,
              "W": -4.735931
            },
            {
              "X": -0.26913497,
              "Y": -0.3227079,
              "Z": -0.45497885,
              "W": 0.282095
            },
            {
              "X": 0.01,
              "Y": 0.01,
              "Z": 0.01,
              "W": 1.0
            },
            {
              "X": 0.0,
              "Y": 0.0,
              "Z": 0.0,
              "W": 1.0
            }
          ],
          "CoordinateScale": {
            "X": 0.2421875,
            "Y": 0.484375
          },
          "CoordinateBias": {
            "X": 0.00390625,
            "Y": 0.0078125
          },
          "InvUniformPenumbraSize": {
            "X": 0.0,
            "Y": 0.0,
            "Z": 0.0,
            "W": 1.0
          },
          "bShadowChannelValid": [
            false,
            false,
            false,
            false
          ],
          "LightGuids": [
            "89698FFA-4F93B075-6DABA59B-0257D39B",
            "6938A531-4666229B-D438FCBA-C2C81595",
            "F5B5499D-4E86C315-53D0B498-7F159297",
            "6DC4FE64-4447B9A5-6C09CA84-7E96F320",
            "EE3601BF-4741A7BF-26E791B5-0F09B138",
            "51BD0747-40B8D23F-C9297784-B3E754F1",
            "EC9B1A16-406D20A1-AEA42BB9-A83F1F41",
            "146AF705-4C8A9F5B-4E760986-62927C9C",
            "6EECFC35-4840F2B5-5DB141AD-798E4273",
            "A27D322D-49EA9F15-B2C2EBBF-566CF1C6",
            "D9E4D333-48792B87-8DC2D689-6030B0D6"
          ]
        },
        "IrrelevantLights": [
          "ACE03AAE-426E1985-A4708681-FFC40418",
          "1DB94F57-4012680D-67735494-8853B8C1"
        ],
        "PerInstanceLightmapData": []
      },
      "9E04802F4A5A4287585945BBF5D4F82B": {
        "LightMap": {
          "Textures": [
            {
              "ObjectName": "LightMapTexture2D'Area011_Objects_BuiltData:HQ_Lightmap1_8'",
              "ObjectPath": "/Game/Carrot4/Maps/Main/Area/Area011/Sublevels/Area011_Objects_BuiltData.1"
            },
            null
          ],
          "SkyOcclusionTexture": {
            "ObjectName": "LightMapTexture2D'Area011_Objects_BuiltData:SkyOcclusion1_8'",
            "ObjectPath": "/Game/Carrot4/Maps/Main/Area/Area011/Sublevels/Area011_Objects_BuiltData.2"
          },
          "AOMaterialMaskTexture": {
            "ObjectName": "LightMapTexture2D'Area011_Objects_BuiltData:AOMaterialMask1_8'",
            "ObjectPath": "/Game/Carrot4/Maps/Main/Area/Area011/Sublevels/Area011_Objects_BuiltData.0"
          },
          "VirtualTextures": [
            null,
            null
          ],
          "ScaleVectors": [
            {
              "X": 0.80278325,
              "Y": 0.3051529,
              "Z": 0.5527023,
              "W": 4.374666
            },
            {
              "X": 0.51176673,
              "Y": 0.46313334,
              "Z": 0.86760896,
              "W": 0.0
            },
            {
              "X": 0.0,
              "Y": 0.0,
              "Z": 0.0,
              "W": 1.0
            },
            {
              "X": 0.0,
              "Y": 0.0,
              "Z": 0.0,
              "W": 1.0
            }
          ],
          "AddVectors": [
            {
              "X": 1.064127,
              "Y": 0.6715844,
              "Z": 0.39720142,
              "W": -4.9475675
            },
            {
              "X": -0.23534933,
              "Y": -0.23491432,
              "Z": -0.4655991,
              "W": 0.282095
            },
            {
              "X": 0.01,
              "Y": 0.01,
              "Z": 0.01,
              "W": 1.0
            },
            {
              "X": 0.0,
              "Y": 0.0,
              "Z": 0.0,
              "W": 1.0
            }
          ],
          "CoordinateScale": {
            "X": 0.2421875,
            "Y": 0.484375
          },
          "CoordinateBias": {
            "X": 0.25390625,
            "Y": 0.0078125
          },
          "InvUniformPenumbraSize": {
            "X": 0.0,
            "Y": 0.0,
            "Z": 0.0,
            "W": 1.0
          },
          "bShadowChannelValid": [
            false,
            false,
            false,
            false
          ],
          "LightGuids": [
            "89698FFA-4F93B075-6DABA59B-0257D39B",
            "6938A531-4666229B-D438FCBA-C2C81595",
            "F5B5499D-4E86C315-53D0B498-7F159297",
            "6DC4FE64-4447B9A5-6C09CA84-7E96F320",
            "EE3601BF-4741A7BF-26E791B5-0F09B138",
            "51BD0747-40B8D23F-C9297784-B3E754F1",
            "EC9B1A16-406D20A1-AEA42BB9-A83F1F41",
            "146AF705-4C8A9F5B-4E760986-62927C9C",
            "6EECFC35-4840F2B5-5DB141AD-798E4273",
            "A27D322D-49EA9F15-B2C2EBBF-566CF1C6",
            "D9E4D333-48792B87-8DC2D689-6030B0D6"
          ]
        },
        "IrrelevantLights": [
          "ACE03AAE-426E1985-A4708681-FFC40418",
          "1DB94F57-4012680D-67735494-8853B8C1"
        ],
        "PerInstanceLightmapData": []
      },
      "491DEB25422D0AB0C3802DAEEF12ED72": {
        "LightMap": {
          "Textures": [
            {
              "ObjectName": "LightMapTexture2D'Area011_Objects_BuiltData:HQ_Lightmap1_8'",
              "ObjectPath": "/Game/Carrot4/Maps/Main/Area/Area011/Sublevels/Area011_Objects_BuiltData.1"
            },
            null
          ],
          "SkyOcclusionTexture": {
            "ObjectName": "LightMapTexture2D'Area011_Objects_BuiltData:SkyOcclusion1_8'",
            "ObjectPath": "/Game/Carrot4/Maps/Main/Area/Area011/Sublevels/Area011_Objects_BuiltData.2"
          },
          "AOMaterialMaskTexture": {
            "ObjectName": "LightMapTexture2D'Area011_Objects_BuiltData:AOMaterialMask1_8'",
            "ObjectPath": "/Game/Carrot4/Maps/Main/Area/Area011/Sublevels/Area011_Objects_BuiltData.0"
          },
          "VirtualTextures": [
            null,
            null
          ],
          "ScaleVectors": [
            {
              "X": 0.6977762,
              "Y": 0.2571786,
              "Z": 0.558453,
              "W": 2.7269428
            },
            {
              "X": 0.48550603,
              "Y": 0.69313985,
              "Z": 0.64936,
              "W": 0.0
            },
            {
              "X": 0.0,
              "Y": 0.0,
              "Z": 0.0,
              "W": 1.0
            },
            {
              "X": 0.0,
              "Y": 0.0,
              "Z": 0.0,
              "W": 1.0
            }
          ],
          "AddVectors": [
            {
              "X": 1.0963854,
              "Y": 0.7340086,
              "Z": 0.25971472,
              "W": -0.75154775
            },
            {
              "X": -0.24870868,
              "Y": -0.34092382,
              "Z": -0.31149885,
              "W": 0.282095
            },
            {
              "X": 0.01,
              "Y": 0.01,
              "Z": 0.01,
              "W": 1.0
            },
            {
              "X": 0.0,
              "Y": 0.0,
              "Z": 0.0,
              "W": 1.0
            }
          ],
          "CoordinateScale": {
            "X": 0.2421875,
            "Y": 0.484375
          },
          "CoordinateBias": {
            "X": 0.00390625,
            "Y": 0.5078125
          },
          "InvUniformPenumbraSize": {
            "X": 0.0,
            "Y": 0.0,
            "Z": 0.0,
            "W": 1.0
          },
          "bShadowChannelValid": [
            false,
            false,
            false,
            false
          ],
          "LightGuids": [
            "89698FFA-4F93B075-6DABA59B-0257D39B",
            "6938A531-4666229B-D438FCBA-C2C81595",
            "F5B5499D-4E86C315-53D0B498-7F159297",
            "EE3601BF-4741A7BF-26E791B5-0F09B138",
            "51BD0747-40B8D23F-C9297784-B3E754F1",
            "EC9B1A16-406D20A1-AEA42BB9-A83F1F41",
            "146AF705-4C8A9F5B-4E760986-62927C9C",
            "6EECFC35-4840F2B5-5DB141AD-798E4273",
            "A27D322D-49EA9F15-B2C2EBBF-566CF1C6",
            "D9E4D333-48792B87-8DC2D689-6030B0D6"
          ]
        },
        "ShadowMap": {
          "Texture": {
            "ObjectName": "ShadowMapTexture2D'Area011_Objects_BuiltData:ShadowMapTexture2D_1'",
            "ObjectPath": "/Game/Carrot4/Maps/Main/Area/Area011/Sublevels/Area011_Objects_BuiltData.4"
          },
          "CoordinateScale": {
            "X": 0.484375,
            "Y": 0.96875
          },
          "CoordinateBias": {
            "X": 0.0078125,
            "Y": 0.015625
          },
          "bChannelValid": [
            true,
            false,
            false,
            false
          ],
          "InvUniformPenumbraSize": {
            "X": 1.0,
            "Y": 0.0,
            "Z": 0.0,
            "W": 0.0
          },
          "LightGuids": [
            "ACE03AAE-426E1985-A4708681-FFC40418"
          ]
        },
        "IrrelevantLights": [
          "1DB94F57-4012680D-67735494-8853B8C1"
        ],
        "PerInstanceLightmapData": []
      }
    },
    "LightBuildData": {
      "013CE4B74AA4578F3E4A18B9822F4DAB": {
        "ShadowMapChannel": -1,
        "DepthMap": {
          "WorldToLight": {
            "M00": 0.71407413,
            "M01": 1.1920929E-07,
            "M02": 6.8119593E-10,
            "M03": 2.3841858E-07,
            "M10": -1.8626445E-09,
            "M11": 0.71407396,
            "M12": -1.06436865E-11,
            "M13": -3.7252903E-09,
            "M20": -0.49999976,
            "M21": -0.49999994,
            "M22": -0.0028571426,
            "M23": -0.9999999,
            "M30": 1219.9404,
            "M31": -1776.56,
            "M32": 1.5760405,
            "M33": 551.6142
          },
          "ShadowMapSizeX": 24,
          "ShadowMapSizeY": 24,
          "DepthSamples": [
            {
              "Encoded": 14809
            },
            {
              "Encoded": 14809
            },
            {
              "Encoded": 14809
            },
            {
              "Encoded": 14809
            },
            {
              "Encoded": 14809
            },
            {
              "Encoded": 14809
            },
            {
              "Encoded": 14801
            },
            {
              "Encoded": 14802
            },
            {
              "Encoded": 14802
            },
            {
              "Encoded": 14803
            },
            {
              "Encoded": 14803
            },
            {
              "Encoded": 14803
            },
            {
              "Encoded": 14803
            },
            {
              "Encoded": 14803
            },
            {
              "Encoded": 14803
            },
            {
              "Encoded": 14803
            },
            {
              "Encoded": 14803
            },
            {
              "Encoded": 14803
            },
            {
              "Encoded": 14803
            },
            {
              "Encoded": 14801
            },
            {
              "Encoded": 14800
            },
            {
              "Encoded": 14798
            },
            {
              "Encoded": 14793
            },
            {
              "Encoded": 14791
            },
            {
              "Encoded": 14809
            },
            {
              "Encoded": 14809
            },
            {
              "Encoded": 14809
            },
            {
              "Encoded": 14809
            },
            {
              "Encoded": 14809
            },
            {
              "Encoded": 14809
            },
            {
              "Encoded": 14803
            },
            {
              "Encoded": 14803
            },
            {
              "Encoded": 14803
            },
            {
              "Encoded": 14803
            },
            {
              "Encoded": 14803
            },
            {
              "Encoded": 14803
            },
            {
              "Encoded": 14803
            },
            {
              "Encoded": 14803
            },
            {
              "Encoded": 14803
            },
            {
              "Encoded": 14803
            },
            {
              "Encoded": 14803
            },
            {
              "Encoded": 14803
            },
            {
              "Encoded": 14803
            },
            {
              "Encoded": 14802
            },
            {
              "Encoded": 14800
            },
            {
              "Encoded": 14798
            },
            {
              "Encoded": 14794
            },
            {
              "Encoded": 14791
            },
            {
              "Encoded": 14809
            },
            {
              "Encoded": 14809
            },
            {
              "Encoded": 14809
            },
            {
              "Encoded": 14809
            },
            {
              "Encoded": 14809
            },
            {
              "Encoded": 14809
            },
            {
              "Encoded": 14803
            },
            {
              "Encoded": 14803
            },
            {
              "Encoded": 14803
            },
            {
              "Encoded": 14803
            },
            {
              "Encoded": 14803
            },
            {
              "Encoded": 14803
            },
            {
              "Encoded": 14803
            },
            {
              "Encoded": 14803
            },
            {
              "Encoded": 14803
            },
            {
              "Encoded": 14803
            },
            {
              "Encoded": 14803
            },
            {
              "Encoded": 14803
            },
            {
              "Encoded": 14803
            },
            {
              "Encoded": 14802
            },
            {
              "Encoded": 14800
            },
            {
              "Encoded": 14798
            },
            {
              "Encoded": 14794
            },
            {
              "Encoded": 14790
            },
            {
              "Encoded": 14463
            },
            {
              "Encoded": 14809
            },
            {
              "Encoded": 14809
            },
            {
              "Encoded": 14809
            },
            {
              "Encoded": 14809
            },
            {
              "Encoded": 14809
            },
            {
              "Encoded": 14803
            },
            {
              "Encoded": 14803
            },
            {
              "Encoded": 14803
            },
            {
              "Encoded": 14803
            },
            {
              "Encoded": 14803
            },
            {
              "Encoded": 14803
            },
            {
              "Encoded": 14803
            },
            {
              "Encoded": 14803
            },
            {
              "Encoded": 14803
            },
            {
              "Encoded": 14803
            },
            {
              "Encoded": 14803
            },
            {
              "Encoded": 14803
            },
            {
              "Encoded": 14803
            },
            {
              "Encoded": 14802
            },
            {
              "Encoded": 14800
            },
            {
              "Encoded": 14798
            },
            {
              "Encoded": 14794
            },
            {
              "Encoded": 14790
            },
            {
              "Encoded": 14457
            },
            {
              "Encoded": 14472
            },
            {
              "Encoded": 14809
            },
            {
              "Encoded": 14809
            },
            {
              "Encoded": 14809
            },
            {
              "Encoded": 14809
            },
            {
              "Encoded": 14802
            },
            {
              "Encoded": 14803
            },
            {
              "Encoded": 14803
            },
            {
              "Encoded": 14803
            },
            {
              "Encoded": 14803
            },
            {
              "Encoded": 14802
            },
            {
              "Encoded": 14802
            },
            {
              "Encoded": 14802
            },
            {
              "Encoded": 14802
            },
            {
              "Encoded": 14802
            },
            {
              "Encoded": 14802
            },
            {
              "Encoded": 14802
            },
            {
              "Encoded": 14802
            },
            {
              "Encoded": 14801
            },
            {
              "Encoded": 14799
            },
            {
              "Encoded": 14797
            },
            {
              "Encoded": 14794
            },
            {
              "Encoded": 14789
            },
            {
              "Encoded": 14457
            },
            {
              "Encoded": 14512
            },
            {
              "Encoded": 14615
            },
            {
              "Encoded": 14738
            },
            {
              "Encoded": 14809
            },
            {
              "Encoded": 14809
            },
            {
              "Encoded": 14801
            },
            {
              "Encoded": 14802
            },
            {
              "Encoded": 14802
            },
            {
              "Encoded": 14802
            },
            {
              "Encoded": 14802
            },
            {
              "Encoded": 14802
            },
            {
              "Encoded": 14802
            },
            {
              "Encoded": 14802
            },
            {
              "Encoded": 14802
            },
            {
              "Encoded": 14802
            },
            {
              "Encoded": 14802
            },
            {
              "Encoded": 14801
            },
            {
              "Encoded": 14801
            },
            {
              "Encoded": 14800
            },
            {
              "Encoded": 14798
            },
            {
              "Encoded": 14797
            },
            {
              "Encoded": 14793
            },
            {
              "Encoded": 14789
            },
            {
              "Encoded": 14462
            },
            {
              "Encoded": 14555
            },
            {
              "Encoded": 14666
            },
            {
              "Encoded": 14799
            },
            {
              "Encoded": 14809
            },
            {
              "Encoded": 14809
            },
            {
              "Encoded": 14801
            },
            {
              "Encoded": 14801
            },
            {
              "Encoded": 14801
            },
            {
              "Encoded": 14801
            },
            {
              "Encoded": 14801
            },
            {
              "Encoded": 14801
            },
            {
              "Encoded": 14801
            },
            {
              "Encoded": 14801
            },
            {
              "Encoded": 14801
            },
            {
              "Encoded": 14801
            },
            {
              "Encoded": 14801
            },
            {
              "Encoded": 14801
            },
            {
              "Encoded": 14801
            },
            {
              "Encoded": 14800
            },
            {
              "Encoded": 14799
            },
            {
              "Encoded": 14798
            },
            {
              "Encoded": 14794
            },
            {
              "Encoded": 14790
            },
            {
              "Encoded": 14500
            },
            {
              "Encoded": 14602
            },
            {
              "Encoded": 14721
            },
            {
              "Encoded": 14809
            },
            {
              "Encoded": 14809
            },
            {
              "Encoded": 14809
            },
            {
              "Encoded": 14801
            },
            {
              "Encoded": 14801
            },
            {
              "Encoded": 14801
            },
            {
              "Encoded": 14801
            },
            {
              "Encoded": 14801
            },
            {
              "Encoded": 14801
            },
            {
              "Encoded": 14801
            },
            {
              "Encoded": 14801
            },
            {
              "Encoded": 14801
            },
            {
              "Encoded": 14801
            },
            {
              "Encoded": 14801
            },
            {
              "Encoded": 14801
            },
            {
              "Encoded": 14801
            },
            {
              "Encoded": 14801
            },
            {
              "Encoded": 14800
            },
            {
              "Encoded": 14799
            },
            {
              "Encoded": 14795
            },
            {
              "Encoded": 14792
            },
            {
              "Encoded": 14809
            },
            {
              "Encoded": 14652
            },
            {
              "Encoded": 14782
            },
            {
              "Encoded": 14809
            },
            {
              "Encoded": 14809
            },
            {
              "Encoded": 14809
            },
            {
              "Encoded": 14801
            },
            {
              "Encoded": 14801
            },
            {
              "Encoded": 14801
            },
            {
              "Encoded": 14801
            },
            {
              "Encoded": 14801
            },
            {
              "Encoded": 14801
            },
            {
              "Encoded": 14801
            },
            {
              "Encoded": 14801
            },
            {
              "Encoded": 14801
            },
            {
              "Encoded": 14801
            },
            {
              "Encoded": 14801
            },
            {
              "Encoded": 14801
            },
            {
              "Encoded": 14801
            },
            {
              "Encoded": 14801
            },
            {
              "Encoded": 14800
            },
            {
              "Encoded": 14800
            },
            {
              "Encoded": 14796
            },
            {
              "Encoded": 14793
            },
            {
              "Encoded": 14809
            },
            {
              "Encoded": 14809
            },
            {
              "Encoded": 14809
            },
            {
              "Encoded": 14809
            },
            {
              "Encoded": 14809
            },
            {
              "Encoded": 14809
            },
            {
              "Encoded": 14801
            },
            {
              "Encoded": 14801
            },
            {
              "Encoded": 14801
            },
            {
              "Encoded": 14801
            },
            {
              "Encoded": 14801
            },
            {
              "Encoded": 14801
            },
            {
              "Encoded": 14801
            },
            {
              "Encoded": 14801
            },
            {
              "Encoded": 14801
            },
            {
              "Encoded": 14801
            },
            {
              "Encoded": 14801
            },
            {
              "Encoded": 14801
            },
            {
              "Encoded": 14801
            },
            {
              "Encoded": 14801
            },
            {
              "Encoded": 14801
            },
            {
              "Encoded": 14800
            },
            {
              "Encoded": 14797
            },
            {
              "Encoded": 14794
            },
            {
              "Encoded": 14809
            },
            {
              "Encoded": 14809
            },
            {
              "Encoded": 14809
            },
            {
              "Encoded": 14809
            },
            {
              "Encoded": 14809
            },
            {
              "Encoded": 14809
            },
            {
              "Encoded": 14801
            },
            {
              "Encoded": 14801
            },
            {
              "Encoded": 14801
            },
            {
              "Encoded": 14801
            },
            {
              "Encoded": 14801
            },
            {
              "Encoded": 14801
            },
            {
              "Encoded": 14801
            },
            {
              "Encoded": 14801
            },
            {
              "Encoded": 14801
            },
            {
              "Encoded": 14801
            },
            {
              "Encoded": 14801
            },
            {
              "Encoded": 14801
            },
            {
              "Encoded": 14801
            },
            {
              "Encoded": 14801
            },
            {
              "Encoded": 14801
            },
            {
              "Encoded": 14801
            },
            {
              "Encoded": 14798
            },
            {
              "Encoded": 14795
            },
            {
              "Encoded": 14809
            },
            {
              "Encoded": 14809
            },
            {
              "Encoded": 14809
            },
            {
              "Encoded": 14809
            },
            {
              "Encoded": 14809
            },
            {
              "Encoded": 14809
            },
            {
              "Encoded": 14801
            },
            {
              "Encoded": 14801
            },
            {
              "Encoded": 14801
            },
            {
              "Encoded": 14801
            },
            {
              "Encoded": 14801
            },
            {
              "Encoded": 14801
            },
            {
              "Encoded": 14801
            },
            {
              "Encoded": 14801
            },
            {
              "Encoded": 14801
            },
            {
              "Encoded": 14801
            },
            {
              "Encoded": 14801
            },
            {
              "Encoded": 14801
            },
            {
              "Encoded": 14801
            },
            {
              "Encoded": 14801
            },
            {
              "Encoded": 14801
            },
            {
              "Encoded": 14801
            },
            {
              "Encoded": 14798
            },
            {
              "Encoded": 14795
            },
            {
              "Encoded": 14809
            },
            {
              "Encoded": 14809
            },
            {
              "Encoded": 14809
            },
            {
              "Encoded": 14809
            },
            {
              "Encoded": 14809
            },
            {
              "Encoded": 14809
            },
            {
              "Encoded": 14801
            },
            {
              "Encoded": 14801
            },
            {
              "Encoded": 14801
            },
            {
              "Encoded": 14801
            },
            {
              "Encoded": 14801
            },
            {
              "Encoded": 14801
            },
            {
              "Encoded": 14801
            },
            {
              "Encoded": 14801
            },
            {
              "Encoded": 14801
            },
            {
              "Encoded": 14801
            },
            {
              "Encoded": 14801
            },
            {
              "Encoded": 14801
            },
            {
              "Encoded": 14801
            },
            {
              "Encoded": 14801
            },
            {
              "Encoded": 14801
            },
            {
              "Encoded": 14801
            },
            {
              "Encoded": 14798
            },
            {
              "Encoded": 14795
            },
            {
              "Encoded": 14809
            },
            {
              "Encoded": 14809
            },
            {
              "Encoded": 14809
            },
            {
              "Encoded": 14809
            },
            {
              "Encoded": 14809
            },
            {
              "Encoded": 14809
            },
            {
              "Encoded": 14801
            },
            {
              "Encoded": 14801
            },
            {
              "Encoded": 14801
            },
            {
              "Encoded": 14801
            },
            {
              "Encoded": 14801
            },
            {
              "Encoded": 14801
            },
            {
              "Encoded": 14801
            },
            {
              "Encoded": 14801
            },
            {
              "Encoded": 14801
            },
            {
              "Encoded": 14801
            },
            {
              "Encoded": 14801
            },
            {
              "Encoded": 14801
            },
            {
              "Encoded": 14801
            },
            {
              "Encoded": 14801
            },
            {
              "Encoded": 14801
            },
            {
              "Encoded": 14801
            },
            {
              "Encoded": 14798
            },
            {
              "Encoded": 14795
            },
            {
              "Encoded": 14809
            },
            {
              "Encoded": 14809
            },
            {
              "Encoded": 14809
            },
            {
              "Encoded": 14809
            },
            {
              "Encoded": 14809
            },
            {
              "Encoded": 14809
            },
            {
              "Encoded": 14801
            },
            {
              "Encoded": 14801
            },
            {
              "Encoded": 14801
            },
            {
              "Encoded": 14801
            },
            {
              "Encoded": 14801
            },
            {
              "Encoded": 14801
            },
            {
              "Encoded": 14801
            },
            {
              "Encoded": 14801
            },
            {
              "Encoded": 14801
            },
            {
              "Encoded": 14801
            },
            {
              "Encoded": 14801
            },
            {
              "Encoded": 14801
            },
            {
              "Encoded": 14801
            },
            {
              "Encoded": 14801
            },
            {
              "Encoded": 14801
            },
            {
              "Encoded": 14800
            },
            {
              "Encoded": 14798
            },
            {
              "Encoded": 14795
            },
            {
              "Encoded": 14809
            },
            {
              "Encoded": 14809
            },
            {
              "Encoded": 14809
            },
            {
              "Encoded": 14809
            },
            {
              "Encoded": 14809
            },
            {
              "Encoded": 14809
            },
            {
              "Encoded": 14809
            },
            {
              "Encoded": 14809
            },
            {
              "Encoded": 14809
            },
            {
              "Encoded": 14809
            },
            {
              "Encoded": 14809
            },
            {
              "Encoded": 14809
            },
            {
              "Encoded": 14809
            },
            {
              "Encoded": 14809
            },
            {
              "Encoded": 14809
            },
            {
              "Encoded": 14809
            },
            {
              "Encoded": 14809
            },
            {
              "Encoded": 14809
            },
            {
              "Encoded": 14809
            },
            {
              "Encoded": 14809
            },
            {
              "Encoded": 14809
            },
            {
              "Encoded": 14809
            },
            {
              "Encoded": 14809
            },
            {
              "Encoded": 14809
            },
            {
              "Encoded": 14809
            },
            {
              "Encoded": 14809
            },
            {
              "Encoded": 14809
            },
            {
              "Encoded": 14809
            },
            {
              "Encoded": 14809
            },
            {
              "Encoded": 14809
            },
            {
              "Encoded": 14809
            },
            {
              "Encoded": 14809
            },
            {
              "Encoded": 14809
            },
            {
              "Encoded": 14809
            },
            {
              "Encoded": 14809
            },
            {
              "Encoded": 14809
            },
            {
              "Encoded": 14809
            },
            {
              "Encoded": 14809
            },
            {
              "Encoded": 14809
            },
            {
              "Encoded": 14809
            },
            {
              "Encoded": 14809
            },
            {
              "Encoded": 14809
            },
            {
              "Encoded": 14809
            },
            {
              "Encoded": 14809
            },
            {
              "Encoded": 14809
            },
            {
              "Encoded": 14809
            },
            {
              "Encoded": 14809
            },
            {
              "Encoded": 14809
            },
            {
              "Encoded": 14809
            },
            {
              "Encoded": 14809
            },
            {
              "Encoded": 14809
            },
            {
              "Encoded": 14809
            },
            {
              "Encoded": 14809
            },
            {
              "Encoded": 14809
            },
            {
              "Encoded": 14809
            },
            {
              "Encoded": 14809
            },
            {
              "Encoded": 14809
            },
            {
              "Encoded": 14809
            },
            {
              "Encoded": 14809
            },
            {
              "Encoded": 14809
            },
            {
              "Encoded": 14809
            },
            {
              "Encoded": 14809
            },
            {
              "Encoded": 14809
            },
            {
              "Encoded": 14809
            },
            {
              "Encoded": 14809
            },
            {
              "Encoded": 14809
            },
            {
              "Encoded": 14809
            },
            {
              "Encoded": 14809
            },
            {
              "Encoded": 14809
            },
            {
              "Encoded": 14809
            },
            {
              "Encoded": 14809
            },
            {
              "Encoded": 14809
            },
            {
              "Encoded": 14809
            },
            {
              "Encoded": 14809
            },
            {
              "Encoded": 14809
            },
            {
              "Encoded": 14809
            },
            {
              "Encoded": 14809
            },
            {
              "Encoded": 14809
            },
            {
              "Encoded": 14809
            },
            {
              "Encoded": 14809
            },
            {
              "Encoded": 14809
            },
            {
              "Encoded": 14809
            },
            {
              "Encoded": 14809
            },
            {
              "Encoded": 14809
            },
            {
              "Encoded": 14809
            },
            {
              "Encoded": 14809
            },
            {
              "Encoded": 14809
            },
            {
              "Encoded": 14809
            },
            {
              "Encoded": 14809
            },
            {
              "Encoded": 14809
            },
            {
              "Encoded": 14809
            },
            {
              "Encoded": 14809
            },
            {
              "Encoded": 14809
            },
            {
              "Encoded": 14809
            },
            {
              "Encoded": 14809
            },
            {
              "Encoded": 14809
            },
            {
              "Encoded": 14809
            },
            {
              "Encoded": 14809
            },
            {
              "Encoded": 14809
            },
            {
              "Encoded": 14809
            },
            {
              "Encoded": 14809
            },
            {
              "Encoded": 14809
            },
            {
              "Encoded": 14809
            },
            {
              "Encoded": 14809
            },
            {
              "Encoded": 14809
            },
            {
              "Encoded": 14809
            },
            {
              "Encoded": 14809
            },
            {
              "Encoded": 14809
            },
            {
              "Encoded": 14809
            },
            {
              "Encoded": 14809
            },
            {
              "Encoded": 14809
            },
            {
              "Encoded": 14809
            },
            {
              "Encoded": 14809
            },
            {
              "Encoded": 14809
            },
            {
              "Encoded": 14809
            },
            {
              "Encoded": 14809
            },
            {
              "Encoded": 14809
            },
            {
              "Encoded": 14809
            },
            {
              "Encoded": 14809
            },
            {
              "Encoded": 14809
            },
            {
              "Encoded": 14809
            },
            {
              "Encoded": 14809
            },
            {
              "Encoded": 14809
            },
            {
              "Encoded": 14809
            },
            {
              "Encoded": 14809
            },
            {
              "Encoded": 14809
            },
            {
              "Encoded": 14809
            },
            {
              "Encoded": 14809
            },
            {
              "Encoded": 14809
            },
            {
              "Encoded": 14809
            },
            {
              "Encoded": 14809
            },
            {
              "Encoded": 14809
            },
            {
              "Encoded": 14809
            },
            {
              "Encoded": 14809
            },
            {
              "Encoded": 14809
            },
            {
              "Encoded": 14809
            },
            {
              "Encoded": 14809
            },
            {
              "Encoded": 14809
            },
            {
              "Encoded": 14809
            },
            {
              "Encoded": 14809
            },
            {
              "Encoded": 14809
            },
            {
              "Encoded": 14809
            },
            {
              "Encoded": 14809
            },
            {
              "Encoded": 14809
            },
            {
              "Encoded": 14809
            },
            {
              "Encoded": 14809
            },
            {
              "Encoded": 14809
            },
            {
              "Encoded": 14809
            },
            {
              "Encoded": 14809
            },
            {
              "Encoded": 14809
            },
            {
              "Encoded": 14809
            },
            {
              "Encoded": 14809
            },
            {
              "Encoded": 14809
            },
            {
              "Encoded": 14809
            },
            {
              "Encoded": 14809
            },
            {
              "Encoded": 14809
            },
            {
              "Encoded": 14809
            },
            {
              "Encoded": 14809
            },
            {
              "Encoded": 14809
            },
            {
              "Encoded": 14809
            },
            {
              "Encoded": 14809
            },
            {
              "Encoded": 14809
            },
            {
              "Encoded": 14809
            },
            {
              "Encoded": 14809
            },
            {
              "Encoded": 14809
            },
            {
              "Encoded": 14809
            },
            {
              "Encoded": 14809
            },
            {
              "Encoded": 14809
            },
            {
              "Encoded": 14809
            },
            {
              "Encoded": 14809
            },
            {
              "Encoded": 14809
            },
            {
              "Encoded": 14809
            },
            {
              "Encoded": 14809
            },
            {
              "Encoded": 14809
            },
            {
              "Encoded": 14809
            },
            {
              "Encoded": 14809
            },
            {
              "Encoded": 14809
            },
            {
              "Encoded": 14809
            },
            {
              "Encoded": 14809
            },
            {
              "Encoded": 14809
            },
            {
              "Encoded": 14809
            },
            {
              "Encoded": 14809
            },
            {
              "Encoded": 14809
            },
            {
              "Encoded": 14809
            },
            {
              "Encoded": 14809
            },
            {
              "Encoded": 14809
            },
            {
              "Encoded": 14809
            },
            {
              "Encoded": 14809
            },
            {
              "Encoded": 14809
            },
            {
              "Encoded": 14809
            },
            {
              "Encoded": 14809
            },
            {
              "Encoded": 14809
            },
            {
              "Encoded": 14809
            },
            {
              "Encoded": 14809
            },
            {
              "Encoded": 14809
            },
            {
              "Encoded": 14809
            },
            {
              "Encoded": 14809
            },
            {
              "Encoded": 14809
            },
            {
              "Encoded": 14809
            },
            {
              "Encoded": 14809
            },
            {
              "Encoded": 14809
            },
            {
              "Encoded": 14809
            },
            {
              "Encoded": 14809
            },
            {
              "Encoded": 14809
            },
            {
              "Encoded": 14809
            },
            {
              "Encoded": 14809
            },
            {
              "Encoded": 14809
            },
            {
              "Encoded": 14809
            },
            {
              "Encoded": 14809
            },
            {
              "Encoded": 14809
            },
            {
              "Encoded": 14809
            },
            {
              "Encoded": 14809
            },
            {
              "Encoded": 14809
            },
            {
              "Encoded": 14809
            },
            {
              "Encoded": 14809
            },
            {
              "Encoded": 14809
            }
          ]
        }
      }
    }
  },
  {
    "Type": "ShadowMapTexture2D",
    "Name": "ShadowMapTexture2D_1",
    "Outer": "Area011_Objects_BuiltData",
    "Class": "UScriptClass'ShadowMapTexture2D'",
    "Properties": {
      "ShadowmapFlags": "SMF_Streamed",
      "ImportedSize": {
        "X": 128,
        "Y": 64
      },
      "SRGB": false
    },
    "SizeX": 128,
    "SizeY": 64,
    "PackedData": 1,
    "PixelFormat": "PF_G8",
    "FirstMipToSerialize": 0,
    "Mips": [
      {
        "BulkData": {
          "BulkDataFlags": "BULKDATA_PayloadAtEndOfFile | BULKDATA_PayloadInSeperateFile | BULKDATA_Force_NOT_InlinePayload | BULKDATA_NoOffsetFixUp",
          "ElementCount": 8192,
          "SizeOnDisk": 8192,
          "OffsetInFile": "0x1C000"
        },
        "SizeX": 128,
        "SizeY": 64,
        "SizeZ": 1
      },
      {
        "BulkData": {
          "BulkDataFlags": "BULKDATA_SingleUse | BULKDATA_ForceInlinePayload",
          "ElementCount": 2048,
          "SizeOnDisk": 2048,
          "OffsetInFile": "0x16ABE"
        },
        "SizeX": 64,
        "SizeY": 32,
        "SizeZ": 1
      },
      {
        "BulkData": {
          "BulkDataFlags": "BULKDATA_SingleUse | BULKDATA_ForceInlinePayload",
          "ElementCount": 512,
          "SizeOnDisk": 512,
          "OffsetInFile": "0x172E2"
        },
        "SizeX": 32,
        "SizeY": 16,
        "SizeZ": 1
      },
      {
        "BulkData": {
          "BulkDataFlags": "BULKDATA_SingleUse | BULKDATA_ForceInlinePayload",
          "ElementCount": 128,
          "SizeOnDisk": 128,
          "OffsetInFile": "0x17506"
        },
        "SizeX": 16,
        "SizeY": 8,
        "SizeZ": 1
      },
      {
        "BulkData": {
          "BulkDataFlags": "BULKDATA_SingleUse | BULKDATA_ForceInlinePayload",
          "ElementCount": 32,
          "SizeOnDisk": 32,
          "OffsetInFile": "0x175AA"
        },
        "SizeX": 8,
        "SizeY": 4,
        "SizeZ": 1
      },
      {
        "BulkData": {
          "BulkDataFlags": "BULKDATA_SingleUse | BULKDATA_ForceInlinePayload",
          "ElementCount": 8,
          "SizeOnDisk": 8,
          "OffsetInFile": "0x175EE"
        },
        "SizeX": 4,
        "SizeY": 2,
        "SizeZ": 1
      },
      {
        "BulkData": {
          "BulkDataFlags": "BULKDATA_SingleUse | BULKDATA_ForceInlinePayload",
          "ElementCount": 2,
          "SizeOnDisk": 2,
          "OffsetInFile": "0x1761A"
        },
        "SizeX": 2,
        "SizeY": 1,
        "SizeZ": 1
      },
      {
        "BulkData": {
          "BulkDataFlags": "BULKDATA_SingleUse | BULKDATA_ForceInlinePayload",
          "ElementCount": 1,
          "SizeOnDisk": 1,
          "OffsetInFile": "0x17640"
        },
        "SizeX": 1,
        "SizeY": 1,
        "SizeZ": 1
      }
    ]
  }
]