[
  {
    "Internal name": "OTABANKCARDBLANK",
    "Name": "Deity's Portrait",
    "Floor": 0,
    "Translate": {
      "X": 250.1875,
      "Y": 1396.2273,
      "Z": 5.0251007
    }
  },
  {
    "Internal name": "OTAHANDSPINNER",
    "Name": "Space Spinner",
    "Floor": 0,
    "Translate": {
      "X": -422.31677,
      "Y": 121.45154,
      "Z": 80.630066
    }
  },
  {
    "Internal name": "OTATRAINC",
    "Name": "Leisure Car",
    "Floor": 0,
    "Translate": {
      "X": -1080.2877,
      "Y": 1356.2539,
      "Z": 82.0
    }
  },
  {
    "Internal name": "OTAPAINTSPNK",
    "Name": "Captivation Goo",
    "Floor": 0,
    "Translate": {
      "X": -1308.9535,
      "Y": 772.74536,
      "Z": 194.0
    }
  },
  {
    "Internal name": "OTAPINBADGEA",
    "Name": "Blast Shield",
    "Floor": 0,
    "Translate": {
      "X": 888.0,
      "Y": 1372.0,
      "Z": 125.0
    }
  },
  {
    "Internal name": "OTABANKCARDD",
    "Name": "Love Emblem",
    "Floor": 0,
    "Translate": {
      "X": 870.0,
      "Y": 1370.0,
      "Z": 100.0
    }
  },
  {
    "Internal name": "OTABANKCARDE",
    "Name": "Money Emblem",
    "Floor": 0,
    "Translate": {
      "X": -1010.625,
      "Y": 952.2815,
      "Z": 155.0251
    }
  },
  {
    "Internal name": "OTABANKCARDF",
    "Name": "Work Emblem",
    "Floor": 0,
    "Translate": {
      "X": 705.75256,
      "Y": -413.9436,
      "Z": 55.0251
    }
  },
  {
    "Internal name": "OTAPAPERBALLOON",
    "Name": "Divine Balloon",
    "Floor": 0,
    "Translate": {
      "X": -1370.0,
      "Y": -1383.0,
      "Z": 185.3001
    }
  },
  {
    "Internal name": "OTABANKCARDBLANK2",
    "Name": "Devil's Portrait",
    "Floor": 0,
    "Translate": {
      "X": 335.6194,
      "Y": -1163.9039,
      "Z": 103.7751
    }
  },
  {
    "Internal name": "OTAPUDDING",
    "Name": "Jiggle-Jiggle",
    "Floor": 0,
    "Translate": {
      "X": -218.0,
      "Y": 929.0,
      "Z": 69.81809
    }
  }
]