{
  "LF007": {
    "LF007_Area500_Talk_Intro_00": "[Npc:Icon chara=\"Leaf08\"/][UE:Meta key=\"6098334a7dcf40109b5486c4918474bb\" Scale=\"1\"/][Npc:Motion name=\"Surprise\"/]怎么会这样！[etc:Wait frame=\"15\"/]\r\n那家伙竟然又出现在这里！[System:PageBreak ][UE:Meta key=\"6098334a7dcf40109b5486c4918474bb\" Scale=\"1\"/][Npc:Motion name=\"AngryFaceOnly2\"/]到底要妨碍我几次才肯罢休！[System:PageBreak ][UE:Meta key=\"6098334a7dcf40109b5486c4918474bb\" Scale=\"1\"/][Npc:Motion name=\"AngryFaceOnly\"/]呃，我说的就是那家伙啦！[etc:Wait frame=\"15\"/]\r\n你那群同伴的驾驶员[Npc:EmphasisStart NpcName=\"Pilot\"/]伯纳[Npc:EmphasisEnd/]！[System:PageBreak ][UE:Meta key=\"6098334a7dcf40109b5486c4918474bb\" Scale=\"1\"/][Npc:Motion name=\"Yare\"/]⋯⋯我是[Npc:EmphasisStart NpcName=\"Leaf08\"/]圣纳[Npc:EmphasisEnd/]，[etc:Wait frame=\"8\"/]现在是受雇于其他公司的驾驶员，[etc:Wait frame=\"8\"/]\r\n那家伙跟我之间有一些过节⋯⋯",
    "LF007_Area500_Talk_Hint_01_01": "[Npc:Icon chara=\"Leaf08\"/][UE:Meta key=\"5e2660bcafe54a72a191ee6b47a61f9d\" Scale=\"1\"/][Npc:Motion name=\"Talk\"/]据说我出生那天，[etc:Wait frame=\"8\"/]那家伙也在同一间\r\n医院的隔壁病床上，睡得跟死猪一样。[System:PageBreak ][UE:Meta key=\"5e2660bcafe54a72a191ee6b47a61f9d\" Scale=\"1\"/][Npc:Motion name=\"YareFaceOnly\"/]真的是打从出生就结下的孽缘⋯⋯[etc:Wait frame=\"15\"/]\r\n不知道为什么，无论走到哪里都能看到那家伙。",
    "LF007_Area500_Talk_Hint_01_02": "[Npc:Icon chara=\"Leaf08\"/][UE:Meta key=\"2161d1af06fa4391b3e5996b197a2e00\" Scale=\"1\"/][Npc:Motion name=\"Think\"/]我到现在都还记得[etc:Wait frame=\"8\"/]\r\n小学运动会上的障碍接力赛⋯⋯[System:PageBreak ][UE:Meta key=\"2161d1af06fa4391b3e5996b197a2e00\" Scale=\"1\"/][Npc:Motion name=\"AngryFaceOnly2\"/]身为最后一棒的我，直到终点前都还是第一名。[etc:Wait frame=\"15\"/]\r\n一直到最后的障碍⋯⋯寻找糖果之前！[System:PageBreak ][UE:Meta key=\"2161d1af06fa4391b3e5996b197a2e00\" Scale=\"1\"/][Npc:Motion name=\"Sad\"/]那家伙冲刺的速度飞快⋯⋯[etc:Wait frame=\"15\"/]\r\n这点我认同。[System:PageBreak ][UE:Meta key=\"2161d1af06fa4391b3e5996b197a2e00\" Scale=\"1\"/]但至少应该留一颗给我吧⋯⋯[etc:Wait frame=\"15\"/]\r\n我的糖果⋯⋯",
    "LF007_Area500_Talk_Hint_01_03": "[Npc:Icon chara=\"Leaf08\"/][UE:Meta key=\"52400da4d05748e7ab1b739269a405c6\" Scale=\"1\"/][Npc:Motion name=\"Yes\"/]进入大学之后，我离开故乡的星球，[etc:Wait frame=\"8\"/]\r\n原以为从此就可以摆脱他的纠缠⋯⋯[System:PageBreak ][UE:Meta key=\"52400da4d05748e7ab1b739269a405c6\" Scale=\"1\"/][Npc:Motion name=\"SurpriseFaceOnly\"/]当我怀着希望抵达学生宿舍的时候，[etc:Wait frame=\"8\"/]\r\n我在屋外就听见房间里响起那家伙高亢的笑声！[System:PageBreak ][UE:Meta key=\"52400da4d05748e7ab1b739269a405c6\" Scale=\"1\"/][Npc:Motion name=\"Talk02\"/]“窄归窄，依然是快乐的My Room！”[System:PageBreak ][UE:Meta key=\"52400da4d05748e7ab1b739269a405c6\" Scale=\"1\"/][Npc:Motion name=\"Yare\"/]房间早已化为那家伙的仓库⋯⋯",
    "LF007_Area500_Talk_Hint_02_01": "[Npc:Icon chara=\"Leaf08\"/][UE:Meta key=\"e2b6b3e1434b480ba2cae767bf3c24a2\" Scale=\"1\"/][Npc:Motion name=\"Yare\"/]毕业后，我进入一间在太空站卖便当的公司，[etc:Wait frame=\"8\"/]\r\n结果卖不赢对手的新商品⋯⋯倒闭了。[System:PageBreak ][UE:Meta key=\"e2b6b3e1434b480ba2cae767bf3c24a2\" Scale=\"1\"/][Npc:Motion name=\"AngryFaceOnly2\"/]对，就是那家伙开发的[etc:Wait frame=\"8\"/]\r\n“一天一罐！以饮为食”这个商品！[System:PageBreak ][UE:Meta key=\"e2b6b3e1434b480ba2cae767bf3c24a2\" Scale=\"1\"/][Npc:Motion name=\"Glad02\"/]“解开绑便当的绳子也很烦！”[System:PageBreak ][UE:Meta key=\"e2b6b3e1434b480ba2cae767bf3c24a2\" Scale=\"1\"/][Npc:Motion name=\"SadFaceOnly2\"/]那家伙竟是出于这种动机开发出新商品，[etc:Wait frame=\"8\"/]\r\n真是令人无法接受⋯⋯",
    "LF007_Area500_Talk_Hint_02_02": "[Npc:Icon chara=\"Leaf08\"/][UE:Meta key=\"9e1a000b08814f9b9033903a84577927\" Scale=\"1\"/][Npc:Motion name=\"Think\"/]自从第一间公司倒闭之后，[etc:Wait frame=\"8\"/]\r\n我就在各星球之间不断换工作⋯⋯[System:PageBreak ][UE:Meta key=\"9e1a000b08814f9b9033903a84577927\" Scale=\"1\"/][Npc:Motion name=\"YareFaceOnly\"/]乐透的预测师、占卜师、[etc:Wait frame=\"8\"/]咖啡店店长⋯⋯[etc:Wait frame=\"8\"/]\r\n甚至还曾立下志向想成为编剧。[System:PageBreak ][UE:Meta key=\"9e1a000b08814f9b9033903a84577927\" Scale=\"1\"/][Npc:Motion name=\"Yes\"/]我从不后悔自己曾经做过这么多职业，[etc:Wait frame=\"15\"/]\r\n因为这些经验日后都成了我的人生食粮。",
    "LF007_Area500_Talk_Hint_02_03": "[Npc:Icon chara=\"Leaf08\"/][UE:Meta key=\"80d6e89bb56146d2a52e82eedaf378b0\" Scale=\"1\"/][Npc:Motion name=\"Talk\"/]我立下宏愿要考取大型宇宙船的执照，[etc:Wait frame=\"8\"/]\r\n于是前往举办集训的行星。[System:PageBreak ][UE:Meta key=\"80d6e89bb56146d2a52e82eedaf378b0\" Scale=\"1\"/][Npc:Motion name=\"Talk02FaceOnly\"/]Man To Man是一间\r\n很热门的驾驶员培训学校⋯⋯[System:PageBreak ][UE:Meta key=\"80d6e89bb56146d2a52e82eedaf378b0\" Scale=\"1\"/][Npc:Motion name=\"Sad\"/]但坐在教官席上的却是那家伙。[etc:Wait frame=\"15\"/]\r\n取得执照前的那3个月，我们从早到晚都形影不离⋯⋯[System:PageBreak ][UE:Meta key=\"80d6e89bb56146d2a52e82eedaf378b0\" Scale=\"1\"/]我连特技飞行都学了不少。",
    "LF007_Area500_Talk_Hint_02_04": "[Npc:Icon chara=\"Leaf08\"/][UE:Meta key=\"9eef233acace4779a67367eb599c2d91\" Scale=\"1\"/][Npc:Motion name=\"Yes\"/]我在之前的公司也是担任驾驶员，[etc:Wait frame=\"8\"/]\r\n有一天，总经理要来现场视察⋯⋯[System:PageBreak ][UE:Meta key=\"9eef233acace4779a67367eb599c2d91\" Scale=\"1\"/][Npc:Motion name=\"TalkFaceOnly\"/]从鲜艳的特技表演专用机[etc:Wait frame=\"8\"/]\r\n一跃而下的人就是⋯⋯[System:PageBreak ][UE:Meta key=\"9eef233acace4779a67367eb599c2d91\" Scale=\"1\"/][Npc:Motion name=\"Glad02\"/]“哦！My Soulmate！[etc:Wait frame=\"8\"/]好久不见！”[System:PageBreak ][UE:Meta key=\"9eef233acace4779a67367eb599c2d91\" Scale=\"1\"/][Npc:Motion name=\"Yare\"/]打从那天开始，我就一次又一次[etc:Wait frame=\"8\"/]\r\n陪着那家伙进行所谓特技飞行的视察⋯⋯",
    "LF007_Area500_Talk_Hint_02_05": "[Npc:Icon chara=\"Leaf08\"/][UE:Meta key=\"bd18b9db3e314b39b6e977dbe78c6782\" Scale=\"1\"/][Npc:Motion name=\"Sad\"/]自从我进入公司就受到[Npc:EmphasisStart NpcName=\"Leaf06\"/]娃娃吉[Npc:EmphasisEnd/]不少照顾⋯⋯[etc:Wait frame=\"15\"/]\r\n我很担心娃娃吉会因为这次的事情累倒。",
    "LF007_Area500_Talk_Hint_02_06": "[Npc:Icon chara=\"Leaf08\"/][UE:Meta key=\"5a69fbddd3f7458bb51a8d96b5374d4e\" Scale=\"1\"/][Npc:Motion name=\"Talk\"/]我对自己操作宇宙船的技术很有自信⋯⋯[etc:Wait frame=\"8\"/]\r\n但万万没想到会陷入这样的事态。[System:PageBreak ][UE:Meta key=\"5a69fbddd3f7458bb51a8d96b5374d4e\" Scale=\"1\"/][Npc:Motion name=\"ThinkFaceOnly\"/]但是那家伙明明技术远高于我，[etc:Wait frame=\"8\"/]\r\n却也一样坠机了，实在令人费解⋯⋯",
    "LF007_Area500_Talk_Hint_02_07": "[Npc:Icon chara=\"Leaf08\"/][UE:Meta key=\"39bfdf53406b488dacd8bda6fdc1df9c\" Scale=\"1\"/][Npc:Motion name=\"Yare\"/]在我成为叶子人的那段时间，一直有幻听的情况⋯⋯[System:PageBreak ][UE:Meta key=\"39bfdf53406b488dacd8bda6fdc1df9c\" Scale=\"1\"/][Npc:Motion name=\"Glad02FaceOnly\"/]“Hey！Let's 当多虑！”[System:PageBreak ][UE:Meta key=\"39bfdf53406b488dacd8bda6fdc1df9c\" Scale=\"1\"/][Npc:Motion name=\"Sad\"/]那个声音让我回想起宇宙船的集训讲习⋯⋯[etc:Wait frame=\"15\"/]\r\n就像做恶梦一样。",
    "LF007_Area500_Talk_Hint_03_01": "[Npc:Icon chara=\"Leaf08\"/][UE:Meta key=\"6cfcc49a284949acbb24bb288da2fd30\" Scale=\"1\"/][Npc:Motion name=\"Talk\"/]假如这次能够平安回去，[etc:Wait frame=\"8\"/]\r\n我想成为星旅的正式员工。[System:PageBreak ][UE:Meta key=\"6cfcc49a284949acbb24bb288da2fd30\" Scale=\"1\"/][Npc:Motion name=\"YesFaceOnly\"/]希望能活用我丰富的职涯，[etc:Wait frame=\"8\"/]\r\n多少替[Npc:EmphasisStart NpcName=\"Leaf06\"/]娃娃吉[Npc:EmphasisEnd/]分担一些辛劳。",
    "LF007_Area500_Talk_Hint_03_02": "[Npc:Icon chara=\"Leaf08\"/][UE:Meta key=\"d6e9a48ac822418fb18c26ea1e18f452\" Scale=\"1\"/][Npc:Motion name=\"Talk\"/]据说我出生那天，[etc:Wait frame=\"8\"/]那家伙也在同一间\r\n医院的隔壁病床上，睡得跟死猪一样。[System:PageBreak ][UE:Meta key=\"d6e9a48ac822418fb18c26ea1e18f452\" Scale=\"1\"/][Npc:Motion name=\"YareFaceOnly\"/]真的是打从出生就结下的孽缘⋯⋯[etc:Wait frame=\"15\"/]\r\n不知道为什么，无论走到哪里都能看到那家伙。",
    "LF007_Area500_Talk_Hint_03_03": "[Npc:Icon chara=\"Leaf08\"/][UE:Meta key=\"57d22fb4b8f24efbab8e7df40adde1bd\" Scale=\"1\"/][Npc:Motion name=\"Think\"/]我到现在都还记得[etc:Wait frame=\"8\"/]\r\n小学运动会上的障碍接力赛⋯⋯[System:PageBreak ][UE:Meta key=\"57d22fb4b8f24efbab8e7df40adde1bd\" Scale=\"1\"/][Npc:Motion name=\"AngryFaceOnly2\"/]身为最后一棒的我，直到终点前都还是第一名。[etc:Wait frame=\"15\"/]\r\n一直到最后的障碍⋯⋯寻找糖果之前！[System:PageBreak ][UE:Meta key=\"57d22fb4b8f24efbab8e7df40adde1bd\" Scale=\"1\"/][Npc:Motion name=\"Sad\"/]那家伙冲刺的速度飞快⋯⋯[etc:Wait frame=\"15\"/]\r\n这点我认同。[System:PageBreak ][UE:Meta key=\"57d22fb4b8f24efbab8e7df40adde1bd\" Scale=\"1\"/]但至少应该留一颗给我吧⋯⋯[etc:Wait frame=\"15\"/]\r\n我的糖果⋯⋯",
    "LF007_Area500_Talk_Hint_03_04": "[Npc:Icon chara=\"Leaf08\"/][UE:Meta key=\"c4592e7283ee4f9cb84799a013dd56f5\" Scale=\"1\"/][Npc:Motion name=\"Yes\"/]进入大学之后，我离开故乡的星球，[etc:Wait frame=\"8\"/]\r\n原以为从此就可以摆脱他的纠缠⋯⋯[System:PageBreak ][UE:Meta key=\"c4592e7283ee4f9cb84799a013dd56f5\" Scale=\"1\"/][Npc:Motion name=\"SurpriseFaceOnly\"/]当我怀着希望抵达学生宿舍的时候，[etc:Wait frame=\"8\"/]\r\n我在屋外就听见房间里响起那家伙高亢的笑声！[System:PageBreak ][UE:Meta key=\"c4592e7283ee4f9cb84799a013dd56f5\" Scale=\"1\"/][Npc:Motion name=\"Talk02\"/]“窄归窄，依然是快乐的My Room！”[System:PageBreak ][UE:Meta key=\"c4592e7283ee4f9cb84799a013dd56f5\" Scale=\"1\"/][Npc:Motion name=\"Yare\"/]房间早已化为那家伙的仓库⋯⋯",
    "LF007_Area500_Talk_Hint_03_05": "[Npc:Icon chara=\"Leaf08\"/][UE:Meta key=\"bcaf84c6d49e46ee9e4810516c7d37ee\" Scale=\"1\"/][Npc:Motion name=\"Yare\"/]毕业后，我进入一间在太空站卖便当的公司，[etc:Wait frame=\"8\"/]\r\n结果卖不赢对手的新商品⋯⋯倒闭了。[System:PageBreak ][UE:Meta key=\"bcaf84c6d49e46ee9e4810516c7d37ee\" Scale=\"1\"/][Npc:Motion name=\"AngryFaceOnly2\"/]对，就是那家伙开发的[etc:Wait frame=\"8\"/]\r\n“一天一罐！以饮为食”这个商品！[System:PageBreak ][UE:Meta key=\"bcaf84c6d49e46ee9e4810516c7d37ee\" Scale=\"1\"/][Npc:Motion name=\"Glad02\"/]“解开绑便当的绳子也很烦！”[System:PageBreak ][UE:Meta key=\"bcaf84c6d49e46ee9e4810516c7d37ee\" Scale=\"1\"/][Npc:Motion name=\"SadFaceOnly2\"/]那家伙竟是出于这种动机开发出新商品，[etc:Wait frame=\"8\"/]\r\n真是令人无法接受⋯⋯",
    "LF007_Area500_Talk_Hint_03_06": "[Npc:Icon chara=\"Leaf08\"/][UE:Meta key=\"6094182c522a44ecb1cb021400efef7b\" Scale=\"1\"/][Npc:Motion name=\"Think\"/]自从第一间公司倒闭之后，[etc:Wait frame=\"8\"/]\r\n我就在各星球之间不断换工作⋯⋯[System:PageBreak ][UE:Meta key=\"6094182c522a44ecb1cb021400efef7b\" Scale=\"1\"/][Npc:Motion name=\"YareFaceOnly\"/]乐透的预测师、占卜师、[etc:Wait frame=\"8\"/]咖啡店店长⋯⋯[etc:Wait frame=\"8\"/]\r\n甚至还曾立下志向想成为编剧。[System:PageBreak ][UE:Meta key=\"6094182c522a44ecb1cb021400efef7b\" Scale=\"1\"/][Npc:Motion name=\"Yes\"/]我从不后悔自己曾经做过这么多职业，[etc:Wait frame=\"15\"/]\r\n因为这些经验日后都成了我的人生食粮。",
    "LF007_Area500_Talk_Hint_03_07": "[Npc:Icon chara=\"Leaf08\"/][UE:Meta key=\"07a815d65d8542e78b528f98361d9458\" Scale=\"1\"/][Npc:Motion name=\"Talk\"/]我立下宏愿要考取大型宇宙船的执照，[etc:Wait frame=\"8\"/]\r\n于是前往举办集训的行星。[System:PageBreak ][UE:Meta key=\"07a815d65d8542e78b528f98361d9458\" Scale=\"1\"/][Npc:Motion name=\"Talk02FaceOnly\"/]Man To Man是一间\r\n很热门的驾驶员培训学校⋯⋯[System:PageBreak ][UE:Meta key=\"07a815d65d8542e78b528f98361d9458\" Scale=\"1\"/][Npc:Motion name=\"Sad\"/]但坐在教官席上的却是那家伙。[etc:Wait frame=\"15\"/]\r\n取得执照前的那3个月，我们从早到晚都形影不离⋯⋯[System:PageBreak ][UE:Meta key=\"07a815d65d8542e78b528f98361d9458\" Scale=\"1\"/]我连特技飞行都学了不少。",
    "LF007_Area500_Talk_Hint_03_08": "[Npc:Icon chara=\"Leaf08\"/][UE:Meta key=\"429bd914ada44780a49c3a2128baa24c\" Scale=\"1\"/][Npc:Motion name=\"Yes\"/]我在之前的公司也是担任驾驶员，[etc:Wait frame=\"8\"/]\r\n有一天，总经理要来现场视察⋯⋯[System:PageBreak ][UE:Meta key=\"429bd914ada44780a49c3a2128baa24c\" Scale=\"1\"/][Npc:Motion name=\"TalkFaceOnly\"/]从鲜艳的特技表演专用机[etc:Wait frame=\"8\"/]\r\n一跃而下的人就是⋯⋯[System:PageBreak ][UE:Meta key=\"429bd914ada44780a49c3a2128baa24c\" Scale=\"1\"/][Npc:Motion name=\"Glad02\"/]“哦！My Soulmate！[etc:Wait frame=\"8\"/]好久不见！”[System:PageBreak ][UE:Meta key=\"429bd914ada44780a49c3a2128baa24c\" Scale=\"1\"/][Npc:Motion name=\"Yare\"/]打从那天开始，我就一次又一次[etc:Wait frame=\"8\"/]\r\n陪着那家伙进行所谓特技飞行的视察⋯⋯",
    "LF007_Area500_Talk_Hint_03_09": "[Npc:Icon chara=\"Leaf08\"/][UE:Meta key=\"a8c3b2944148403e95b4dc50394c434c\" Scale=\"1\"/][Npc:Motion name=\"Sad\"/]自从我进入公司就受到[Npc:EmphasisStart NpcName=\"Leaf06\"/]娃娃吉[Npc:EmphasisEnd/]不少照顾⋯⋯[etc:Wait frame=\"15\"/]\r\n我很担心娃娃吉会因为这次的事情累倒。",
    "LF007_Area500_Talk_Hint_03_10": "[Npc:Icon chara=\"Leaf08\"/][UE:Meta key=\"bf161434ce6944219bae1d72ee984eb8\" Scale=\"1\"/][Npc:Motion name=\"Talk\"/]我对自己操作宇宙船的技术很有自信⋯⋯[etc:Wait frame=\"8\"/]\r\n但万万没想到会陷入这样的事态。[System:PageBreak ][UE:Meta key=\"bf161434ce6944219bae1d72ee984eb8\" Scale=\"1\"/][Npc:Motion name=\"ThinkFaceOnly\"/]但是那家伙明明技术远高于我，[etc:Wait frame=\"8\"/]\r\n却也一样坠机了，实在令人费解⋯⋯",
    "LF007_Area500_Talk_Hint_03_11": "[Npc:Icon chara=\"Leaf08\"/][UE:Meta key=\"2ebf66b08a5e4a42b8dde88e4de38abc\" Scale=\"1\"/][Npc:Motion name=\"Yare\"/]在我成为叶子人的那段时间，一直有幻听的情况⋯⋯[System:PageBreak ][UE:Meta key=\"2ebf66b08a5e4a42b8dde88e4de38abc\" Scale=\"1\"/][Npc:Motion name=\"Glad02FaceOnly\"/]“Hey！Let's 当多虑！”[System:PageBreak ][UE:Meta key=\"2ebf66b08a5e4a42b8dde88e4de38abc\" Scale=\"1\"/][Npc:Motion name=\"Sad\"/]那个声音让我回想起宇宙船的集训讲习⋯⋯[etc:Wait frame=\"15\"/]\r\n就像做恶梦一样。",
    "LF007_Area500_Talk_HappyTalk_01": "[Npc:Icon chara=\"Leaf08\"/][UE:Meta key=\"490e0235007c461db484d3dbf3288105\" Scale=\"1\"/][Npc:Motion name=\"Glad\"/]看着你的脸，我就觉得心平气和⋯⋯[etc:Wait frame=\"15\"/]\r\n让我能够暂时忘了那家伙的事。",
    "LF007_Area500_Talk_HappyTalk_02": "[Npc:Icon chara=\"Leaf08\"/][UE:Meta key=\"9cc1e262e2fd412e96638d2078d13baa\" Scale=\"1\"/][Npc:Motion name=\"Yare\"/]当我看着你，就想起自己穿着狗的玩偶装[etc:Wait frame=\"8\"/]\r\n到处发传单的时期⋯⋯",
    "LF007_Area500_Talk_Outro_T01": "[Npc:Icon chara=\"Leaf08\"/][UE:Meta key=\"b98b6eaf9cc6457b962a25d6daee7380\" Scale=\"1\"/][Npc:Motion name=\"Sad\"/]如果不希望那家伙阴魂不散地跟着你，[etc:Wait frame=\"8\"/]\r\n我劝你还是换一张脸比较安全。"
  }
}